Workbook

Sheet Final Recommendation
A1: FINAL RECOMMENDATION – Amber straight-sided jars & launch plan
A2: Updated Oct 9, 2026 with LIVE supplier prices. Volumes: Balance 2,000 · 60ct 500 · 90ct 500 (edit on Inputs). Blue cells are editable; replace with written quotes and everything recalculates.
A3: ⚠ CONFIRMED: Canada charges a 50% surtax on US-MADE glass jars (SOR/2026-186, tariff 7010.90.00, since Sept 8, 2026). It's based on where the jar was made. China-made jars: no duty, no surtax.
A5: 1. THE DECISION
A6: Bottle style | B6: ="Sticking with your CURRENT packer style is cheaper: ~CAD "&TEXT('Packer vs Straight-Sided'!H51,"#,##0")&" less in regular and ~CAD "&TEXT('Packer vs Straight-Sided'!H53,"#,##0")&" less in frosted (see the Packer vs Straight-Sided tab). Packer sizes: Balance 120cc · 60ct 150cc · 90ct 250cc. The rest of this tab covers the straight-sided route if you prefer that look." -> Sticking with your CURRENT packer style is cheaper: ~CAD 960 less in regular and ~CAD 975 less in frosted (see the Packer vs Straight-Sided tab). Packer sizes: Balance 120cc · 60ct 150cc · 90ct 250cc. The rest of this tab covers the straight-sided route if you prefer that look.
A7: Launch order | B7: 1st: 90ct androgen-balancing (berberine). 2nd: 60ct liver booster, positioned as an add-on to Balance AND the 90ct. Balance moves to the new jar when its jars arrive.
A8: Jar per SKU | B8: Balance → 4 oz (looks like today) · 60ct → 6 oz / 175–190 ml · 90ct → 8 oz (237 ml; ~270 ml brim-full). The 8 oz works whether the 90ct ends up size 0 (~61% full) or 00 (fits).
A9: 90ct (launch first) | B9: Buy 500 × 8 oz LOCALLY now. Cheapest landed: SKS Bottle (free UPS to Ontario, induction-lined caps). Get the jar's country of origin first – if US-made, Uline's 8 oz (Canadian stock) costs about the same.
A10: Balance + 60ct | B10: ="It depends on where Burch's jars are made (ask them). NOT US-made → buy both from Burch in ONE shipment (Plan B): within CAD "&TEXT(ABS(D58),"#,##0")&" of China, with no 3-month wait and no quality risk. US-made (50% surtax) → a China order saves ~CAD "&TEXT(E58,"#,##0")&" (Plan A), if the RFQ meets the table 3 targets." -> It depends on where Burch's jars are made (ask them). NOT US-made → buy both from Burch in ONE shipment (Plan B): within CAD 14 of China, with no 3-month wait and no quality risk. US-made (50% surtax) → a China order saves ~CAD 906 (Plan A), if the RFQ meets the table 3 targets.
A11: Finish | B11: ="Cost-first pick = REGULAR. Frosted adds ~CAD "&TEXT(D59,"#,##0")&" (Plan E vs A), mostly from spray-frosting just 500 × 8 oz locally. Cheaper frosted route: Balance + 60ct frosted from China by sea, and the 90ct frosted jars flown from China (DDP air, ~5–7 weeks incl. production) – see the Packer vs Straight-Sided tab. Frosting everything locally (Plan F) costs far more." -> Cost-first pick = REGULAR. Frosted adds ~CAD 1,374 (Plan E vs A), mostly from spray-frosting just 500 × 8 oz locally. Cheaper frosted route: Balance + 60ct frosted from China by sea, and the 90ct frosted jars flown from China (DDP air, ~5–7 weeks incl. production) – see the Packer vs Straight-Sided tab. Frosting everything locally (Plan F) costs far more.
A12: Cheaper but less certain | B12: ="Plan D (everything from Burch in one shipment, with a 9 oz for the 90ct) saves another ~CAD "&TEXT(D53-D55,"#,##0")&" vs Plan B, but a 9 oz looks only ~54% full if the 90ct ends up size 0. Your call on looks vs savings." -> Plan D (everything from Burch in one shipment, with a 9 oz for the 90ct) saves another ~CAD 544 vs Plan B, but a 9 oz looks only ~54% full if the 90ct ends up size 0. Your call on looks vs savings.
A13: Future reorders | B13: Once volumes grow, move the 90ct to a China 250 ml jar on the same order as Balance + 60ct so all three jars match and freight is shared.
A15: 2. LOCAL JAR FOR THE 90ct – 500 × 8 oz (cheapest landed highlighted; live prices)
A16: Option | B16: Item | C16: Ships from | D16: Currency | E16: Jar price | F16: Cap price (per jar needed) | G16: Notes | H16: FX | I16: Goods (CAD/jar) | J16: Freight & brokerage (CAD/jar) | K16: LANDED regular (CAD/jar) | L16: Landed if jar is US-made (+50% surtax) | M16: LANDED frosted (spray, CAD/jar) | N16: Capacity (ml, nominal) | O16: Looks full if size 0 | P16: Fits size 00? | Q16: Total regular (CAD) | R16: Total frosted (CAD)
A17: SKS Bottle (US) | B17: 40530080.03S 8 oz amber SS 70/400 (case 36) | C17: US | D17: USD | E17: 0.88 | F17: =159.6/Inputs!$B$7 -> 0.3192 | G17: Live $31.68/36. Cap 2101-79B black PP + foam INDUCTION liner, $159.60 per case of 760 (whole case spread over the jars needed). FREE UPS Ground to Ontario on US$500+ → only brokerage applies. Jar origin not stated ('kit assembled in USA'). | H17: =IF(D17="USD",Inputs!$B$10,1) -> 1.424 | I17: =(E17+F17)*H17*(1+Inputs!$B$33) -> 1.7076608 | J17: =Inputs!$B$25/Inputs!$B$7 -> 0.25 | K17: =I17+J17 -> 1.9576608 | L17: =K17+E17*H17*Inputs!$B$34 -> 2.5842208 | M17: =K17+Inputs!$B$37+(Inputs!$B$38+Inputs!$B$39)/Inputs!$B$7 -> 4.3076608 | N17: 237 | O17: ='Capsule Sizing'!$D$30/N17 -> 0.60773326 | P17: =IF('Capsule Sizing'!$E$29/N17>1,"No",IF('Capsule Sizing'!$E$29/N17>'Capsule Sizing'!$B$13,"Yes – snug, test","Yes")) -> Yes – snug, test | Q17: =K17*Inputs!$B$7 -> 978.8304 | R17: =M17*Inputs!$B$7 -> 2153.8304
A18: Bottlestore (US) | B18: 55220042 8 oz amber SS 70-405 (fits 70-400); 272 ml brim-full | C18: US | D18: USD | E18: 0.46 | F18: 0.21 | G18: Live $0.46 (24/ctn). Cap 70400OV black ribbed F217 $0.21 (Made in USA). Freight to Canada extra. Jar origin not stated (their 4 oz is Made in USA). | H18: =IF(D18="USD",Inputs!$B$10,1) -> 1.424 | I18: =(E18+F18)*H18*(1+Inputs!$B$33) -> 0.95408 | J18: =(Inputs!$B$24*Inputs!$B$10+Inputs!$B$25)/Inputs!$B$7 -> 1.3892 | K18: =I18+J18 -> 2.34328 | L18: =K18+E18*H18*Inputs!$B$34 -> 2.6708 | M18: =K18+Inputs!$B$37+(Inputs!$B$38+Inputs!$B$39)/Inputs!$B$7 -> 4.69328 | N18: 237 | O18: ='Capsule Sizing'!$D$30/N18 -> 0.60773326 | P18: =IF('Capsule Sizing'!$E$29/N18>1,"No",IF('Capsule Sizing'!$E$29/N18>'Capsule Sizing'!$B$13,"Yes – snug, test","Yes")) -> Yes – snug, test | Q18: =K18*Inputs!$B$7 -> 1171.64 | R18: =M18*Inputs!$B$7 -> 2346.64
A19: Uline Canada (metal cap) | B19: S-25207 8 oz amber SS, black metal cap, plastisol liner | C19: Canada | D19: CAD | E19: 2.2 | F19: 0 | G19: Live CAD 2.20 at 3+ cases, cap included. Canadian stock (any surtax is already in Uline's price). Metal/plastisol cap can't be induction sealed – use a shrink band. Phenolic version S-24533 CAD 2.35. | H19: =IF(D19="USD",Inputs!$B$10,1) -> 1 | I19: =(E19+F19)*H19*(1+Inputs!$B$33) -> 2.2 | J19: =Inputs!$B$26/Inputs!$B$7 -> 0.3 | K19: =I19+J19 -> 2.5 | L19: =K19 -> 2.5 | M19: =K19+Inputs!$B$37+(Inputs!$B$38+Inputs!$B$39)/Inputs!$B$7 -> 4.85 | N19: 237 | O19: ='Capsule Sizing'!$D$30/N19 -> 0.60773326 | P19: =IF('Capsule Sizing'!$E$29/N19>1,"No",IF('Capsule Sizing'!$E$29/N19>'Capsule Sizing'!$B$13,"Yes – snug, test","Yes")) -> Yes – snug, test | Q19: =K19*Inputs!$B$7 -> 1250 | R19: =M19*Inputs!$B$7 -> 2425
A20: Voyageur (Canada) | B20: GJ-AMB-70-400-8OZ 8 oz amber glass 70-400 | C20: Canada | D20: CAD | E20: 1.95 | F20: 0.54 | G20: Live single-unit price ($2.49 with ribbed cap). No bulk pricing; shape not confirmed straight-sided. Ask for a 500-unit quote. | H20: =IF(D20="USD",Inputs!$B$10,1) -> 1 | I20: =(E20+F20)*H20*(1+Inputs!$B$33) -> 2.49 | J20: =Inputs!$B$26/Inputs!$B$7 -> 0.3 | K20: =I20+J20 -> 2.79 | L20: =K20 -> 2.79 | M20: =K20+Inputs!$B$37+(Inputs!$B$38+Inputs!$B$39)/Inputs!$B$7 -> 5.14 | N20: 237 | O20: ='Capsule Sizing'!$D$30/N20 -> 0.60773326 | P20: =IF('Capsule Sizing'!$E$29/N20>1,"No",IF('Capsule Sizing'!$E$29/N20>'Capsule Sizing'!$B$13,"Yes – snug, test","Yes")) -> Yes – snug, test | Q20: =K20*Inputs!$B$7 -> 1395 | R20: =M20*Inputs!$B$7 -> 2570
A21: Alt: Richards 9 oz (Canada, China-made) | B21: RP-1001A 9 oz amber SS 70-400 | C21: Canada | D21: CAD | E21: 0.99 | F21: 0.25 | G21: Live list price (member price may be lower); 70 mm black PP cap 32110979. No surtax risk. BUT a 9 oz looks only ~54% full if the 90ct is size 0. | H21: =IF(D21="USD",Inputs!$B$10,1) -> 1 | I21: =(E21+F21)*H21*(1+Inputs!$B$33) -> 1.24 | J21: =Inputs!$B$26/Inputs!$B$7 -> 0.3 | K21: =I21+J21 -> 1.54 | L21: =K21 -> 1.54 | M21: =K21+Inputs!$B$37+(Inputs!$B$38+Inputs!$B$39)/Inputs!$B$7 -> 3.89 | N21: 266 | O21: ='Capsule Sizing'!$D$30/N21 -> 0.54147662 | P21: =IF('Capsule Sizing'!$E$29/N21>1,"No",IF('Capsule Sizing'!$E$29/N21>'Capsule Sizing'!$B$13,"Yes – snug, test","Yes")) -> Yes | Q21: =K21*Inputs!$B$7 -> 770 | R21: =M21*Inputs!$B$7 -> 1945
A22: Alt: Burch 9 oz (US) | B22: 1SSA092SGC 9 oz amber SS 70-400 | C22: US | D22: USD | E22: 0.441 | F22: 0.17 | G22: Live $5.29/12 at 40–175 cases; cap 2BP0701PX $0.17. Same ~54% look issue if size 0. Jar origin not stated. | H22: =IF(D22="USD",Inputs!$B$10,1) -> 1.424 | I22: =(E22+F22)*H22*(1+Inputs!$B$33) -> 0.870064 | J22: =(Inputs!$B$24*Inputs!$B$10+Inputs!$B$25)/Inputs!$B$7 -> 1.3892 | K22: =I22+J22 -> 2.259264 | L22: =K22+E22*H22*Inputs!$B$34 -> 2.573256 | M22: =K22+Inputs!$B$37+(Inputs!$B$38+Inputs!$B$39)/Inputs!$B$7 -> 4.609264 | N22: 266 | O22: ='Capsule Sizing'!$D$30/N22 -> 0.54147662 | P22: =IF('Capsule Sizing'!$E$29/N22>1,"No",IF('Capsule Sizing'!$E$29/N22>'Capsule Sizing'!$B$13,"Yes – snug, test","Yes")) -> Yes | Q22: =K22*Inputs!$B$7 -> 1129.632 | R22: =M22*Inputs!$B$7 -> 2304.632
A23: Cheapest 8 oz (used in table 4) → | K23: =MIN(K17:K20) -> 1.9576608 | L23: =MIN(L17:L20) -> 2.5 | M23: =MIN(M17:M20) -> 4.3076608
A25: 3. BALANCE (2,000 × 4 oz) + 60ct (500 × 6 oz) – China order vs buying locally
A26: Go with China ONLY IF the RFQ comes back ≤ US$0.50/jar including a PP cap with induction liner (both sizes, one supplier, matching style) AND LCL door-to-door ≤ CAD 1,100. Otherwise buy locally.
A27: Option / SKU | B27: Source | C27: Jar | D27: Jar + cap (native) | E27: FX | F27: Goods (CAD/jar) | G27: Frosting (CAD/jar) | H27: Freight, brokerage, samples/QC (CAD/jar) | I27: LANDED (CAD/jar) | J27: Surtax if jar is US-made (CAD/jar) | K27: Landed if US-made | L27: Qty | M27: Total (CAD) | N27: Total if US-made (CAD)
A28: 3a. CHINA – regular amber (one LCL shipment)
A29: Balance – 30ct | B29: China direct | C29: ='Regular Finish – Top 3'!B25 -> 120 ml | D29: ='Regular Finish – Top 3'!I25+'Regular Finish – Top 3'!K25 -> 0.49 | E29: ='Regular Finish – Top 3'!L25 -> 1.424 | F29: =D29*E29*(1+Inputs!$B$33) -> 0.69776 | G29: 0 | H29: =(Inputs!$B$28+Inputs!$B$30)/(Inputs!$B$5+Inputs!$B$6) -> 0.664 | I29: =F29+G29+H29 -> 1.36176 | J29: 0 | K29: =I29+J29 -> 1.36176 | L29: =Inputs!$B$5 -> 2000 | M29: =I29*L29 -> 2723.52 | N29: =K29*L29 -> 2723.52
A30: New A – 60ct | B30: China direct | C30: ='Regular Finish – Top 3'!B26 -> 180–190 ml | D30: ='Regular Finish – Top 3'!I26+'Regular Finish – Top 3'!K26 -> 0.55 | E30: ='Regular Finish – Top 3'!L26 -> 1.424 | F30: =D30*E30*(1+Inputs!$B$33) -> 0.7832 | G30: 0 | H30: =(Inputs!$B$28+Inputs!$B$30)/(Inputs!$B$5+Inputs!$B$6) -> 0.664 | I30: =F30+G30+H30 -> 1.4472 | J30: 0 | K30: =I30+J30 -> 1.4472 | L30: =Inputs!$B$6 -> 500 | M30: =I30*L30 -> 723.6 | N30: =K30*L30 -> 723.6
A31: Subtotal | M31: =SUM(M29:M30) -> 3447.12 | N31: =SUM(N29:N30) -> 3447.12
A32: 3b. LOCAL – Burch 4 oz + 6 oz, one US shipment
A33: Balance – 30ct | B33: Burch (US) | C33: ='Regular Finish – Top 3'!B7 -> 4 oz | D33: ='Regular Finish – Top 3'!I7+'Regular Finish – Top 3'!K7 -> 0.61708333 | E33: ='Regular Finish – Top 3'!L7 -> 1.424 | F33: =D33*E33*(1+Inputs!$B$33) -> 0.87872667 | G33: 0 | H33: =(Inputs!$B$18*Inputs!$B$10+Inputs!$B$19)/(Inputs!$B$5+Inputs!$B$6) -> 0.44024 | I33: =F33+G33+H33 -> 1.3189667 | J33: ='Regular Finish – Top 3'!I7*E33*Inputs!$B$34 -> 0.33968333 | K33: =I33+J33 -> 1.65865 | L33: =Inputs!$B$5 -> 2000 | M33: =I33*L33 -> 2637.9333 | N33: =K33*L33 -> 3317.3
A34: New A – 60ct | B34: Burch (US) | C34: ='Regular Finish – Top 3'!B8 -> 6 oz | D34: ='Regular Finish – Top 3'!I8+'Regular Finish – Top 3'!K8 -> 0.8075 | E34: ='Regular Finish – Top 3'!L8 -> 1.424 | F34: =D34*E34*(1+Inputs!$B$33) -> 1.14988 | G34: 0 | H34: =(Inputs!$B$18*Inputs!$B$10+Inputs!$B$19)/(Inputs!$B$5+Inputs!$B$6) -> 0.44024 | I34: =F34+G34+H34 -> 1.59012 | J34: ='Regular Finish – Top 3'!I8*E34*Inputs!$B$34 -> 0.48238 | K34: =I34+J34 -> 2.0725 | L34: =Inputs!$B$6 -> 500 | M34: =I34*L34 -> 795.06 | N34: =K34*L34 -> 1036.25
A35: Subtotal | M35: =SUM(M33:M34) -> 3432.9933 | N35: =SUM(N33:N34) -> 4353.55
A36: 3c. LOCAL – Richards 4 oz (Canada, China-made) + Burch 6 oz (small US shipment)
A37: Balance – 30ct | B37: Richards (Canada) | C37: ='Regular Finish – Top 3'!B34 -> 4 oz | D37: ='Regular Finish – Top 3'!I34+'Regular Finish – Top 3'!K34 -> 1.46 | E37: ='Regular Finish – Top 3'!L34 -> 1 | F37: =D37*E37*(1+Inputs!$B$33) -> 1.46 | G37: 0 | H37: =Inputs!$B$20/Inputs!$B$5 -> 0.15 | I37: =F37+G37+H37 -> 1.61 | J37: 0 | K37: =I37+J37 -> 1.61 | L37: =Inputs!$B$5 -> 2000 | M37: =I37*L37 -> 3220 | N37: =K37*L37 -> 3220
A38: New A – 60ct | B38: Burch (US) | C38: ='Regular Finish – Top 3'!B8 -> 6 oz | D38: ='Regular Finish – Top 3'!I8+'Regular Finish – Top 3'!K8 -> 0.8075 | E38: ='Regular Finish – Top 3'!L8 -> 1.424 | F38: =D38*E38*(1+Inputs!$B$33) -> 1.14988 | G38: 0 | H38: =(Inputs!$B$24*Inputs!$B$10+Inputs!$B$25)/Inputs!$B$6 -> 1.3892 | I38: =F38+G38+H38 -> 2.53908 | J38: ='Regular Finish – Top 3'!I8*E38*Inputs!$B$34 -> 0.48238 | K38: =I38+J38 -> 3.02146 | L38: =Inputs!$B$6 -> 500 | M38: =I38*L38 -> 1269.54 | N38: =K38*L38 -> 1510.73
A39: Subtotal | M39: =SUM(M37:M38) -> 4489.54 | N39: =SUM(N37:N38) -> 4730.73
A40: 3d. CHINA – frosted amber (one LCL shipment)
A41: Balance – 30ct | B41: China direct (frosted) | C41: ='Frosted Finish – Top 3'!B7 -> 120 ml | D41: ='Frosted Finish – Top 3'!I7+'Frosted Finish – Top 3'!K7 -> 0.53 | E41: ='Frosted Finish – Top 3'!L7 -> 1.424 | F41: =D41*E41*(1+Inputs!$B$33) -> 0.75472 | G41: 0 | H41: =(Inputs!$B$28+Inputs!$B$30)/(Inputs!$B$5+Inputs!$B$6) -> 0.664 | I41: =F41+G41+H41 -> 1.41872 | J41: 0 | K41: =I41+J41 -> 1.41872 | L41: =Inputs!$B$5 -> 2000 | M41: =I41*L41 -> 2837.44 | N41: =K41*L41 -> 2837.44
A42: New A – 60ct | B42: China direct (frosted) | C42: ='Frosted Finish – Top 3'!B8 -> 180–190 ml | D42: ='Frosted Finish – Top 3'!I8+'Frosted Finish – Top 3'!K8 -> 0.67 | E42: ='Frosted Finish – Top 3'!L8 -> 1.424 | F42: =D42*E42*(1+Inputs!$B$33) -> 0.95408 | G42: 0 | H42: =(Inputs!$B$28+Inputs!$B$30)/(Inputs!$B$5+Inputs!$B$6) -> 0.664 | I42: =F42+G42+H42 -> 1.61808 | J42: 0 | K42: =I42+J42 -> 1.61808 | L42: =Inputs!$B$6 -> 500 | M42: =I42*L42 -> 809.04 | N42: =K42*L42 -> 809.04
A43: Subtotal | M43: =SUM(M41:M42) -> 3646.48 | N43: =SUM(N41:N42) -> 3646.48
A44: 3e. LOCAL frosted – Burch 4 oz + 6 oz + Canadian spray-frost
A45: Balance – 30ct | B45: Burch + spray frost | C45: ='Regular Finish – Top 3'!B7 -> 4 oz | D45: ='Regular Finish – Top 3'!I7+'Regular Finish – Top 3'!K7 -> 0.61708333 | E45: ='Regular Finish – Top 3'!L7 -> 1.424 | F45: =D45*E45*(1+Inputs!$B$33) -> 0.87872667 | G45: =Inputs!$B$37+(Inputs!$B$38+Inputs!$B$39/2)/Inputs!$B$5 -> 0.85 | H45: =(Inputs!$B$18*Inputs!$B$10+Inputs!$B$19)/(Inputs!$B$5+Inputs!$B$6) -> 0.44024 | I45: =F45+G45+H45 -> 2.1689667 | J45: ='Regular Finish – Top 3'!I7*E45*Inputs!$B$34 -> 0.33968333 | K45: =I45+J45 -> 2.50865 | L45: =Inputs!$B$5 -> 2000 | M45: =I45*L45 -> 4337.9333 | N45: =K45*L45 -> 5017.3
A46: New A – 60ct | B46: Burch + spray frost | C46: ='Regular Finish – Top 3'!B8 -> 6 oz | D46: ='Regular Finish – Top 3'!I8+'Regular Finish – Top 3'!K8 -> 0.8075 | E46: ='Regular Finish – Top 3'!L8 -> 1.424 | F46: =D46*E46*(1+Inputs!$B$33) -> 1.14988 | G46: =Inputs!$B$37+(Inputs!$B$38+Inputs!$B$39/2)/Inputs!$B$6 -> 2.05 | H46: =(Inputs!$B$18*Inputs!$B$10+Inputs!$B$19)/(Inputs!$B$5+Inputs!$B$6) -> 0.44024 | I46: =F46+G46+H46 -> 3.64012 | J46: ='Regular Finish – Top 3'!I8*E46*Inputs!$B$34 -> 0.48238 | K46: =I46+J46 -> 4.1225 | L46: =Inputs!$B$6 -> 500 | M46: =I46*L46 -> 1820.06 | N46: =K46*L46 -> 2061.25
A47: Subtotal | M47: =SUM(M45:M46) -> 6157.9933 | N47: =SUM(N45:N46) -> 7078.55
A48: China jar prices are live listing prices (made-in-china.com) or estimates – the RFQ replaces them. Most low-MOQ China jars come with metal lids; specify PP caps with induction/PS22 liners. Frosted 180 ml at 500 units may hit a higher MOQ.
A50: 4. TOTAL COST BY PLAN (all three SKUs, CAD)
A51: Plan | D51: Total (CAD) | E51: Total if US-made jars (surtax) | F51: Avg per jar | G51: vs bottle+lid benchmark (total)
A52: A. 90ct local 8 oz + Balance & 60ct from CHINA – regular (pick if Burch jars are US-made) | D52: =K23*Inputs!$B$7+M31 -> 4425.9504 | E52: =L23*Inputs!$B$7+N31 -> 4697.12 | F52: =D52/Inputs!$B$8 -> 1.4753168 | G52: =D52-Inputs!$B$15*Inputs!$B$8 -> -5894.0496
A53: B. 90ct local 8 oz + Balance & 60ct from Burch, one shipment – regular (pick if Burch jars are NOT US-made) | D53: =K23*Inputs!$B$7+M35 -> 4411.8237 | E53: =L23*Inputs!$B$7+N35 -> 5603.55 | F53: =D53/Inputs!$B$8 -> 1.4706079 | G53: =D53-Inputs!$B$15*Inputs!$B$8 -> -5908.1763
A54: C. 90ct local 8 oz + Richards 4 oz + Burch 6 oz – regular | D54: =K23*Inputs!$B$7+M39 -> 5468.3704 | E54: =L23*Inputs!$B$7+N39 -> 5980.73 | F54: =D54/Inputs!$B$8 -> 1.8227901 | G54: =D54-Inputs!$B$15*Inputs!$B$8 -> -4851.6296
A55: D. Everything from Burch in one shipment (90ct in 9 oz – borderline look if size 0) – regular | D55: ='Split Plan – Local vs China'!N31 -> 3867.9067 | E55: ='Split Plan – Local vs China'!O31 -> 4945.4 | F55: =D55/Inputs!$B$8 -> 1.2893022 | G55: =D55-Inputs!$B$15*Inputs!$B$8 -> -6452.0933
A56: E. 90ct local 8 oz spray-frosted + Balance & 60ct frosted from CHINA | D56: =M23*Inputs!$B$7+M43 -> 5800.3104 | E56: =M23*Inputs!$B$7+(L23-K23)*Inputs!$B$7+N43 -> 6071.48 | F56: =D56/Inputs!$B$8 -> 1.9334368 | G56: =D56-Inputs!$B$15*Inputs!$B$8 -> -4519.6896
A57: F. 90ct local 8 oz spray-frosted + Burch 4 oz + 6 oz spray-frosted | D57: =M23*Inputs!$B$7+M47 -> 8311.8237 | E57: =M23*Inputs!$B$7+(L23-K23)*Inputs!$B$7+N47 -> 9503.55 | F57: =D57/Inputs!$B$8 -> 2.7706079 | G57: =D57-Inputs!$B$15*Inputs!$B$8 -> -2008.1763
A58: China saving vs local (A vs B): | D58: =D53-D52 -> -14.126667 | E58: =E53-E52 -> 906.43 | F58: Positive = China cheaper. Small at these volumes, so China is only worth it if the RFQ targets in table 3 are met.
A59: Frosted premium (E vs A): | D59: =D56-D52 -> 1374.36 | F59: Most of it is the spray-frost setup on just 500 × 8 oz. Negative 'vs benchmark' = cheaper than the ~$3.44 bottle+lid ceiling.
A61: 5. TIMELINE
A62: Week 0 (now) | B62: Manufacturer: confirm straight-sided jars + tamper seal. Ask Burch and SKS where their jars are made. Request quotes: SKS 8 oz (90ct); Burch 4 oz + 6 oz in one shipment; China RFQ as the backup. Order samples (CPS sends free ones).
A63: Weeks 1–2 | B63: Samples in hand → pour test (30 / 60 / 90 capsules). Decide regular vs frosted. Order 500 × 8 oz for the 90ct (SKS, or Uline if the SKS jar is US-made).
A64: Weeks 2–3 | B64: 8 oz jars arrive (UPS ~1 week) → bottle and LAUNCH the 90ct.
A65: Weeks 2–4 | B65: Balance + 60ct: Burch jars NOT US-made → order from Burch (~2 weeks). US-made → place the China order if the RFQ meets the targets (~8–10 weeks door to door).
A66: When those jars land | B66: LAUNCH the 60ct liver booster when you're ready to space it out; switch Balance to the 4 oz jar when current bottle stock runs out.
A68: 6. WHY THE 90ct LAUNCHES FIRST
A69: • Brings in NEW customers: androgen-driven acne (common in women with PCOS) is a different, large group from Balance's estrogen-driven acne.
A70: • Makes the liver booster easier to sell: launched second, it's an add-on to TWO products and can be offered to both customer groups.
A71: • Strong current demand for berberine, and it starts a PCOS line (possible inositol pairing later). Likely the highest order value.
A72: • Flip it (liver booster first) only if Balance has a large repeat customer base you want to upsell quickly, or marketing cash is tight. Your Hormone Imbalance Quiz results could confirm demand.
A73: • Plan for: berberine side effects (GI) and drug interactions (e.g. metformin, common in PCOS) → clear cautions and support. Product licence (NPN) claim wording per Health Canada.
A75: 7. OPEN ITEMS BEFORE ORDERING
A76: 1. Manufacturer: straight-sided jars OK? Tamper-seal method? Bottle + lid cost (enter on Inputs)?
A77: 2. Country of origin for the SKS 8 oz (and Burch jars if used). US-made = 50% surtax on the jar value; ask a broker whether the remission order could refund it.
A78: 3. China RFQ against the table 3 targets; confirm 180 ml at 500 units, PP caps with induction/PS22 liners, and matching style across sizes.
A79: 4. Freight quotes to your postal code (LCL from China; US shipments). These are the biggest remaining estimates at 500-unit volumes.

Sheet Packer vs Straight-Sided
A1: Current bottle style (amber wide-mouth PACKER) vs STRAIGHT-SIDED jars
A2: Live prices Oct 9, 2026. Same volumes as everywhere else (Inputs). Tamper method = cotton + outer shrink band (no heat seal); shrink bands cost about the same for both styles (~CAD 0.02/unit), so they're left out.
A4: 1. PACKER SIZES THAT FIT (standard sizes are 120 / 150 / 200 / 250cc – nobody stocks 175 or 225cc)
A5: SKU / scenario | B5: 120cc (38-400) | C5: 150cc (45-400) | D5: 200cc (45-400) | E5: 250cc (45-400) | F5: Recommended packer
A6: Capacity nominal / brim-full (cc) | B6: 120 / 135 | C6: 150 / 171 | D6: 200 / 226 | E6: 250 / 275
A7: Balance – 30ct (current) | B7: =IF('Capsule Sizing'!$E$26/135>1,"Too small",IF('Capsule Sizing'!$D$26/120<'Capsule Sizing'!$B$12,"Looks < half ("&TEXT('Capsule Sizing'!$D$26/120,"0%")&")",IF('Capsule Sizing'!$E$26/120>'Capsule Sizing'!$B$13,"Tight – test ("&TEXT('Capsule Sizing'!$D$26/120,"0%")&" full)","OK ("&TEXT('Capsule Sizing'!$D$26/120,"0%")&" full)"))) -> Looks < half (40%) | C7: =IF('Capsule Sizing'!$E$26/171>1,"Too small",IF('Capsule Sizing'!$D$26/150<'Capsule Sizing'!$B$12,"Looks < half ("&TEXT('Capsule Sizing'!$D$26/150,"0%")&")",IF('Capsule Sizing'!$E$26/150>'Capsule Sizing'!$B$13,"Tight – test ("&TEXT('Capsule Sizing'!$D$26/150,"0%")&" full)","OK ("&TEXT('Capsule Sizing'!$D$26/150,"0%")&" full)"))) -> Looks < half (32%) | D7: =IF('Capsule Sizing'!$E$26/226>1,"Too small",IF('Capsule Sizing'!$D$26/200<'Capsule Sizing'!$B$12,"Looks < half ("&TEXT('Capsule Sizing'!$D$26/200,"0%")&")",IF('Capsule Sizing'!$E$26/200>'Capsule Sizing'!$B$13,"Tight – test ("&TEXT('Capsule Sizing'!$D$26/200,"0%")&" full)","OK ("&TEXT('Capsule Sizing'!$D$26/200,"0%")&" full)"))) -> Looks < half (24%) | E7: =IF('Capsule Sizing'!$E$26/275>1,"Too small",IF('Capsule Sizing'!$D$26/250<'Capsule Sizing'!$B$12,"Looks < half ("&TEXT('Capsule Sizing'!$D$26/250,"0%")&")",IF('Capsule Sizing'!$E$26/250>'Capsule Sizing'!$B$13,"Tight – test ("&TEXT('Capsule Sizing'!$D$26/250,"0%")&" full)","OK ("&TEXT('Capsule Sizing'!$D$26/250,"0%")&" full)"))) -> Looks < half (19%) | F7: 120cc (as today)
A8: New A – 60ct (if size 0) | B8: =IF('Capsule Sizing'!$E$28/135>1,"Too small",IF('Capsule Sizing'!$D$28/120<'Capsule Sizing'!$B$12,"Looks < half ("&TEXT('Capsule Sizing'!$D$28/120,"0%")&")",IF('Capsule Sizing'!$E$28/120>'Capsule Sizing'!$B$13,"Tight – test ("&TEXT('Capsule Sizing'!$D$28/120,"0%")&" full)","OK ("&TEXT('Capsule Sizing'!$D$28/120,"0%")&" full)"))) -> Tight – test (80% full) | C8: =IF('Capsule Sizing'!$E$28/171>1,"Too small",IF('Capsule Sizing'!$D$28/150<'Capsule Sizing'!$B$12,"Looks < half ("&TEXT('Capsule Sizing'!$D$28/150,"0%")&")",IF('Capsule Sizing'!$E$28/150>'Capsule Sizing'!$B$13,"Tight – test ("&TEXT('Capsule Sizing'!$D$28/150,"0%")&" full)","OK ("&TEXT('Capsule Sizing'!$D$28/150,"0%")&" full)"))) -> OK (64% full) | D8: =IF('Capsule Sizing'!$E$28/226>1,"Too small",IF('Capsule Sizing'!$D$28/200<'Capsule Sizing'!$B$12,"Looks < half ("&TEXT('Capsule Sizing'!$D$28/200,"0%")&")",IF('Capsule Sizing'!$E$28/200>'Capsule Sizing'!$B$13,"Tight – test ("&TEXT('Capsule Sizing'!$D$28/200,"0%")&" full)","OK ("&TEXT('Capsule Sizing'!$D$28/200,"0%")&" full)"))) -> Looks < half (48%) | E8: =IF('Capsule Sizing'!$E$28/275>1,"Too small",IF('Capsule Sizing'!$D$28/250<'Capsule Sizing'!$B$12,"Looks < half ("&TEXT('Capsule Sizing'!$D$28/250,"0%")&")",IF('Capsule Sizing'!$E$28/250>'Capsule Sizing'!$B$13,"Tight – test ("&TEXT('Capsule Sizing'!$D$28/250,"0%")&" full)","OK ("&TEXT('Capsule Sizing'!$D$28/250,"0%")&" full)"))) -> Looks < half (38%) | F8: 150cc
A9: New A – 60ct (if size 00) | B9: =IF('Capsule Sizing'!$E$27/135>1,"Too small",IF('Capsule Sizing'!$D$27/120<'Capsule Sizing'!$B$12,"Looks < half ("&TEXT('Capsule Sizing'!$D$27/120,"0%")&")",IF('Capsule Sizing'!$E$27/120>'Capsule Sizing'!$B$13,"Tight – test ("&TEXT('Capsule Sizing'!$D$27/120,"0%")&" full)","OK ("&TEXT('Capsule Sizing'!$D$27/120,"0%")&" full)"))) -> Too small | C9: =IF('Capsule Sizing'!$E$27/171>1,"Too small",IF('Capsule Sizing'!$D$27/150<'Capsule Sizing'!$B$12,"Looks < half ("&TEXT('Capsule Sizing'!$D$27/150,"0%")&")",IF('Capsule Sizing'!$E$27/150>'Capsule Sizing'!$B$13,"Tight – test ("&TEXT('Capsule Sizing'!$D$27/150,"0%")&" full)","OK ("&TEXT('Capsule Sizing'!$D$27/150,"0%")&" full)"))) -> Tight – test (85% full) | D9: =IF('Capsule Sizing'!$E$27/226>1,"Too small",IF('Capsule Sizing'!$D$27/200<'Capsule Sizing'!$B$12,"Looks < half ("&TEXT('Capsule Sizing'!$D$27/200,"0%")&")",IF('Capsule Sizing'!$E$27/200>'Capsule Sizing'!$B$13,"Tight – test ("&TEXT('Capsule Sizing'!$D$27/200,"0%")&" full)","OK ("&TEXT('Capsule Sizing'!$D$27/200,"0%")&" full)"))) -> OK (64% full) | E9: =IF('Capsule Sizing'!$E$27/275>1,"Too small",IF('Capsule Sizing'!$D$27/250<'Capsule Sizing'!$B$12,"Looks < half ("&TEXT('Capsule Sizing'!$D$27/250,"0%")&")",IF('Capsule Sizing'!$E$27/250>'Capsule Sizing'!$B$13,"Tight – test ("&TEXT('Capsule Sizing'!$D$27/250,"0%")&" full)","OK ("&TEXT('Capsule Sizing'!$D$27/250,"0%")&" full)"))) -> OK (51% full) | F9: 150cc – tight, pour-test (fits brim-full)
A10: New B – 90ct (if size 0) | B10: =IF('Capsule Sizing'!$E$30/135>1,"Too small",IF('Capsule Sizing'!$D$30/120<'Capsule Sizing'!$B$12,"Looks < half ("&TEXT('Capsule Sizing'!$D$30/120,"0%")&")",IF('Capsule Sizing'!$E$30/120>'Capsule Sizing'!$B$13,"Tight – test ("&TEXT('Capsule Sizing'!$D$30/120,"0%")&" full)","OK ("&TEXT('Capsule Sizing'!$D$30/120,"0%")&" full)"))) -> Too small | C10: =IF('Capsule Sizing'!$E$30/171>1,"Too small",IF('Capsule Sizing'!$D$30/150<'Capsule Sizing'!$B$12,"Looks < half ("&TEXT('Capsule Sizing'!$D$30/150,"0%")&")",IF('Capsule Sizing'!$E$30/150>'Capsule Sizing'!$B$13,"Tight – test ("&TEXT('Capsule Sizing'!$D$30/150,"0%")&" full)","OK ("&TEXT('Capsule Sizing'!$D$30/150,"0%")&" full)"))) -> Tight – test (96% full) | D10: =IF('Capsule Sizing'!$E$30/226>1,"Too small",IF('Capsule Sizing'!$D$30/200<'Capsule Sizing'!$B$12,"Looks < half ("&TEXT('Capsule Sizing'!$D$30/200,"0%")&")",IF('Capsule Sizing'!$E$30/200>'Capsule Sizing'!$B$13,"Tight – test ("&TEXT('Capsule Sizing'!$D$30/200,"0%")&" full)","OK ("&TEXT('Capsule Sizing'!$D$30/200,"0%")&" full)"))) -> OK (72% full) | E10: =IF('Capsule Sizing'!$E$30/275>1,"Too small",IF('Capsule Sizing'!$D$30/250<'Capsule Sizing'!$B$12,"Looks < half ("&TEXT('Capsule Sizing'!$D$30/250,"0%")&")",IF('Capsule Sizing'!$E$30/250>'Capsule Sizing'!$B$13,"Tight – test ("&TEXT('Capsule Sizing'!$D$30/250,"0%")&" full)","OK ("&TEXT('Capsule Sizing'!$D$30/250,"0%")&" full)"))) -> OK (58% full) | F10: 250cc
A11: New B – 90ct (if size 00) | B11: =IF('Capsule Sizing'!$E$29/135>1,"Too small",IF('Capsule Sizing'!$D$29/120<'Capsule Sizing'!$B$12,"Looks < half ("&TEXT('Capsule Sizing'!$D$29/120,"0%")&")",IF('Capsule Sizing'!$E$29/120>'Capsule Sizing'!$B$13,"Tight – test ("&TEXT('Capsule Sizing'!$D$29/120,"0%")&" full)","OK ("&TEXT('Capsule Sizing'!$D$29/120,"0%")&" full)"))) -> Too small | C11: =IF('Capsule Sizing'!$E$29/171>1,"Too small",IF('Capsule Sizing'!$D$29/150<'Capsule Sizing'!$B$12,"Looks < half ("&TEXT('Capsule Sizing'!$D$29/150,"0%")&")",IF('Capsule Sizing'!$E$29/150>'Capsule Sizing'!$B$13,"Tight – test ("&TEXT('Capsule Sizing'!$D$29/150,"0%")&" full)","OK ("&TEXT('Capsule Sizing'!$D$29/150,"0%")&" full)"))) -> Too small | D11: =IF('Capsule Sizing'!$E$29/226>1,"Too small",IF('Capsule Sizing'!$D$29/200<'Capsule Sizing'!$B$12,"Looks < half ("&TEXT('Capsule Sizing'!$D$29/200,"0%")&")",IF('Capsule Sizing'!$E$29/200>'Capsule Sizing'!$B$13,"Tight – test ("&TEXT('Capsule Sizing'!$D$29/200,"0%")&" full)","OK ("&TEXT('Capsule Sizing'!$D$29/200,"0%")&" full)"))) -> Tight – test (96% full) | E11: =IF('Capsule Sizing'!$E$29/275>1,"Too small",IF('Capsule Sizing'!$D$29/250<'Capsule Sizing'!$B$12,"Looks < half ("&TEXT('Capsule Sizing'!$D$29/250,"0%")&")",IF('Capsule Sizing'!$E$29/250>'Capsule Sizing'!$B$13,"Tight – test ("&TEXT('Capsule Sizing'!$D$29/250,"0%")&" full)","OK ("&TEXT('Capsule Sizing'!$D$29/250,"0%")&" full)"))) -> OK (77% full) | F11: 250cc
A12: Balance at ~40% is the same as today (owner accepted). Packers have shoulders, so they tend to look fuller than a straight-sided jar at the same fill. A packer line needs only 2 neck sizes (38 + 45-400) vs 3 for jars.
A14: 2. PACKER OPTIONS – landed cost (bottle + black PP cap + freight/brokerage)
A15: P1. REGULAR – TricorBraun 120 / 150 / 250cc, all three in ONE shipment (glass made in China → no surtax)
A16: Plan / SKU | B16: Supplier | C16: Item | D16: Size | E16: Currency | F16: Bottle price | G16: Cap price (per bottle needed) | H16: FX | I16: Goods (CAD/unit) | J16: Frosting (CAD/unit) | K16: Freight & one-time (CAD/unit) | L16: LANDED (CAD/unit) | M16: Landed if US-made (+50% on glass) | N16: Qty | O16: Total (CAD) | P16: Total if US-made (CAD) | Q16: Notes
A17: Balance – 30ct | B17: TricorBraun (US web store) | C17: 319293 120cc amber packer, 38-400 | D17: 120cc | E17: USD | F17: =677.34/Inputs!$B$5 -> 0.33867 | G17: =261/Inputs!$B$5 -> 0.1305 | H17: =IF(E17="USD",Inputs!$B$10,1) -> 1.424 | I17: =(F17+G17)*H17*(1+Inputs!$B$33) -> 0.66809808 | J17: 0 | K17: =(Inputs!$B$18*Inputs!$B$10+Inputs!$B$19)/Inputs!$B$8 -> 0.36686667 | L17: =I17+J17+K17 -> 1.0349647 | M17: =L17 -> 1.0349647 | N17: =Inputs!$B$5 -> 2000 | O17: =L17*N17 -> 2069.9295 | P17: =M17*N17 -> 2069.9295 | Q17: Live: 18 cases × $37.63 = $677.34 for 2,268 bottles (cheaper than 16 cases at $44.80). Cap 348629 black PP F-217, $261 per case of 2,900. Glass origin China (stated).
A18: New A – 60ct | B18: TricorBraun | C18: 319904 150cc amber packer, 45-400 | D18: 150cc | E18: USD | F18: 0.4167 | G18: =198.53/(Inputs!$B$6+Inputs!$B$7) -> 0.19853 | H18: =IF(E18="USD",Inputs!$B$10,1) -> 1.424 | I18: =(F18+G18)*H18*(1+Inputs!$B$33) -> 0.87608752 | J18: 0 | K18: =(Inputs!$B$18*Inputs!$B$10+Inputs!$B$19)/Inputs!$B$8 -> 0.36686667 | L18: =I18+J18+K18 -> 1.2429542 | M18: =L18 -> 1.2429542 | N18: =Inputs!$B$6 -> 500 | O18: =L18*N18 -> 621.47709 | P18: =M18*N18 -> 621.47709 | Q18: Live: $5.00/case of 12 at 18+ cases. 45-400 black caps come in 2,000-piece cases ($198.53) – shared with the 250cc. Origin China.
A19: New B – 90ct | B19: TricorBraun | C19: 319907 250cc amber packer, 45-400 | D19: 250cc | E19: USD | F19: 0.6117 | G19: =198.53/(Inputs!$B$6+Inputs!$B$7) -> 0.19853 | H19: =IF(E19="USD",Inputs!$B$10,1) -> 1.424 | I19: =(F19+G19)*H19*(1+Inputs!$B$33) -> 1.1537675 | J19: 0 | K19: =(Inputs!$B$18*Inputs!$B$10+Inputs!$B$19)/Inputs!$B$8 -> 0.36686667 | L19: =I19+J19+K19 -> 1.5206342 | M19: =L19 -> 1.5206342 | N19: =Inputs!$B$7 -> 500 | O19: =L19*N19 -> 760.31709 | P19: =M19*N19 -> 760.31709 | Q19: Live: $7.34/case of 12 at 18+ cases. Works for 90ct at size 0 or 00. Origin China.
A20: TOTAL | L20: =O20/Inputs!$B$8 -> 1.1505746 | O20: =SUM(O17:O19) -> 3451.7237 | P20: =SUM(P17:P19) -> 3451.7237
A22: P2. REGULAR – China packers for Balance + 60ct (one LCL) + TricorBraun 250cc for the 90ct (small US shipment)
A23: Plan / SKU | B23: Supplier | C23: Item | D23: Size | E23: Currency | F23: Bottle price | G23: Cap price (per bottle needed) | H23: FX | I23: Goods (CAD/unit) | J23: Frosting (CAD/unit) | K23: Freight & one-time (CAD/unit) | L23: LANDED (CAD/unit) | M23: Landed if US-made (+50% on glass) | N23: Qty | O23: Total (CAD) | P23: Total if US-made (CAD) | Q23: Notes
A24: Balance – 30ct | B24: China – Jinan Snail / NOVA / Advantrio (RFQ) | C24: 120cc amber packer, 38-400 | D24: 120cc | E24: USD | F24: 0.2 | G24: 0.04 | H24: =IF(E24="USD",Inputs!$B$10,1) -> 1.424 | I24: =(F24+G24)*H24*(1+Inputs!$B$33) -> 0.34176 | J24: 0 | K24: =(Inputs!$B$28+Inputs!$B$30)/(Inputs!$B$5+Inputs!$B$6) -> 0.664 | L24: =I24+J24+K24 -> 1.00576 | M24: =L24 -> 1.00576 | N24: =Inputs!$B$5 -> 2000 | O24: =L24*N24 -> 2011.52 | P24: =M24*N24 -> 2011.52 | Q24: Live made-in-china: Snail $0.20 at 1,000+; NOVA $0.058–0.062; Advantrio MOQ 500 (quote). Cap ESTIMATE US$0.04 (may be included).
A25: New A – 60ct | B25: China – Jinan Snail / NOVA / Advantrio (RFQ) | C25: 150cc amber packer, 45-400 | D25: 150cc | E25: USD | F25: 0.2 | G25: 0.04 | H25: =IF(E25="USD",Inputs!$B$10,1) -> 1.424 | I25: =(F25+G25)*H25*(1+Inputs!$B$33) -> 0.34176 | J25: 0 | K25: =(Inputs!$B$28+Inputs!$B$30)/(Inputs!$B$5+Inputs!$B$6) -> 0.664 | L25: =I25+J25+K25 -> 1.00576 | M25: =L25 -> 1.00576 | N25: =Inputs!$B$6 -> 500 | O25: =L25*N25 -> 502.88 | P25: =M25*N25 -> 502.88 | Q25: As above. Confirm 500 per size.
A26: New B – 90ct | B26: TricorBraun | C26: 319907 250cc, 45-400 | D26: 250cc | E26: USD | F26: 0.6117 | G26: 0.2 | H26: =IF(E26="USD",Inputs!$B$10,1) -> 1.424 | I26: =(F26+G26)*H26*(1+Inputs!$B$33) -> 1.1558608 | J26: 0 | K26: =(Inputs!$B$24*Inputs!$B$10+Inputs!$B$25)/Inputs!$B$7 -> 1.3892 | L26: =I26+J26+K26 -> 2.5450608 | M26: =L26 -> 2.5450608 | N26: =Inputs!$B$7 -> 500 | O26: =L26*N26 -> 1272.5304 | P26: =M26*N26 -> 1272.5304 | Q26: Small US shipment for the launch SKU.
A27: TOTAL | L27: =O27/Inputs!$B$8 -> 1.2623101 | O27: =SUM(O24:O26) -> 3786.9304 | P27: =SUM(P24:P26) -> 3786.9304
A29: P3. FROSTED – China frosted packers: Balance + 60ct by sea (LCL); 90ct by DDP AIR so it can launch first (~5–7 weeks incl. production)
A30: Plan / SKU | B30: Supplier | C30: Item | D30: Size | E30: Currency | F30: Bottle price | G30: Cap price (per bottle needed) | H30: FX | I30: Goods (CAD/unit) | J30: Frosting (CAD/unit) | K30: Freight & one-time (CAD/unit) | L30: LANDED (CAD/unit) | M30: Landed if US-made (+50% on glass) | N30: Qty | O30: Total (CAD) | P30: Total if US-made (CAD) | Q30: Notes
A31: Balance – 30ct | B31: China – Jinan Snail (frosted amber) | C31: 120cc frosted amber packer | D31: 120cc | E31: USD | F31: 0.3 | G31: 0.04 | H31: =IF(E31="USD",Inputs!$B$10,1) -> 1.424 | I31: =(F31+G31)*H31*(1+Inputs!$B$33) -> 0.48416 | J31: 0 | K31: =(Inputs!$B$28+Inputs!$B$30)/(Inputs!$B$5+Inputs!$B$6) -> 0.664 | L31: =I31+J31+K31 -> 1.14816 | M31: =L31 -> 1.14816 | N31: =Inputs!$B$5 -> 2000 | O31: =L31*N31 -> 2296.32 | P31: =M31*N31 -> 2296.32 | Q31: Live: Snail frosted amber $0.30 at 1,000–9,999. Confirm 500/size MOQ and whether cap is included.
A32: New A – 60ct | B32: China – Jinan Snail (frosted amber) | C32: 150cc frosted amber packer | D32: 150cc | E32: USD | F32: 0.3 | G32: 0.04 | H32: =IF(E32="USD",Inputs!$B$10,1) -> 1.424 | I32: =(F32+G32)*H32*(1+Inputs!$B$33) -> 0.48416 | J32: 0 | K32: =(Inputs!$B$28+Inputs!$B$30)/(Inputs!$B$5+Inputs!$B$6) -> 0.664 | L32: =I32+J32+K32 -> 1.14816 | M32: =L32 -> 1.14816 | N32: =Inputs!$B$6 -> 500 | O32: =L32*N32 -> 574.08 | P32: =M32*N32 -> 574.08 | Q32: As above.
A33: New B – 90ct | B33: China – Jinan Snail (frosted amber) | C33: 250cc frosted amber packer | D33: 250cc | E33: USD | F33: 0.3 | G33: 0.04 | H33: =IF(E33="USD",Inputs!$B$10,1) -> 1.424 | I33: =(F33+G33)*H33*(1+Inputs!$B$33) -> 0.48416 | J33: 0 | K33: =Inputs!$B$29/Inputs!$B$7 -> 1.74 | L33: =I33+J33+K33 -> 2.22416 | M33: =L33 -> 2.22416 | N33: =Inputs!$B$7 -> 500 | O33: =L33*N33 -> 1112.08 | P33: =M33*N33 -> 1112.08 | Q33: Shipped separately by DDP air (Inputs) for speed. North America has NO frosted amber packers in stock.
A34: TOTAL | L34: =O34/Inputs!$B$8 -> 1.3274933 | O34: =SUM(O31:O33) -> 3982.48 | P34: =SUM(P31:P33) -> 3982.48
A36: P4. FROSTED – China frosted packers for Balance + 60ct + TricorBraun 250cc spray-frosted in Canada for the 90ct
A37: Plan / SKU | B37: Supplier | C37: Item | D37: Size | E37: Currency | F37: Bottle price | G37: Cap price (per bottle needed) | H37: FX | I37: Goods (CAD/unit) | J37: Frosting (CAD/unit) | K37: Freight & one-time (CAD/unit) | L37: LANDED (CAD/unit) | M37: Landed if US-made (+50% on glass) | N37: Qty | O37: Total (CAD) | P37: Total if US-made (CAD) | Q37: Notes
A38: Balance – 30ct | B38: China – Jinan Snail (frosted amber) | C38: 120cc frosted amber packer | D38: 120cc | E38: USD | F38: 0.3 | G38: 0.04 | H38: =IF(E38="USD",Inputs!$B$10,1) -> 1.424 | I38: =(F38+G38)*H38*(1+Inputs!$B$33) -> 0.48416 | J38: 0 | K38: =(Inputs!$B$28+Inputs!$B$30)/(Inputs!$B$5+Inputs!$B$6) -> 0.664 | L38: =I38+J38+K38 -> 1.14816 | M38: =L38 -> 1.14816 | N38: =Inputs!$B$5 -> 2000 | O38: =L38*N38 -> 2296.32 | P38: =M38*N38 -> 2296.32 | Q38: As P3.
A39: New A – 60ct | B39: China – Jinan Snail (frosted amber) | C39: 150cc frosted amber packer | D39: 150cc | E39: USD | F39: 0.3 | G39: 0.04 | H39: =IF(E39="USD",Inputs!$B$10,1) -> 1.424 | I39: =(F39+G39)*H39*(1+Inputs!$B$33) -> 0.48416 | J39: 0 | K39: =(Inputs!$B$28+Inputs!$B$30)/(Inputs!$B$5+Inputs!$B$6) -> 0.664 | L39: =I39+J39+K39 -> 1.14816 | M39: =L39 -> 1.14816 | N39: =Inputs!$B$6 -> 500 | O39: =L39*N39 -> 574.08 | P39: =M39*N39 -> 574.08 | Q39: As P3.
A40: New B – 90ct | B40: TricorBraun + Stanpac spray frost | C40: 319907 250cc, 45-400 | D40: 250cc | E40: USD | F40: 0.6117 | G40: 0.2 | H40: =IF(E40="USD",Inputs!$B$10,1) -> 1.424 | I40: =(F40+G40)*H40*(1+Inputs!$B$33) -> 1.1558608 | J40: =Inputs!$B$37+(Inputs!$B$38+Inputs!$B$39)/Inputs!$B$7 -> 2.35 | K40: =(Inputs!$B$24*Inputs!$B$10+Inputs!$B$25)/Inputs!$B$7 -> 1.3892 | L40: =I40+J40+K40 -> 4.8950608 | M40: =L40 -> 4.8950608 | N40: =Inputs!$B$7 -> 500 | O40: =L40*N40 -> 2447.5304 | P40: =M40*N40 -> 2447.5304 | Q40: Spray-frost setup spread over just 500 bottles; frost finish may not match China's etched frost.
A41: TOTAL | L41: =O41/Inputs!$B$8 -> 1.7726435 | O41: =SUM(O38:O40) -> 5317.9304 | P41: =SUM(P38:P40) -> 5317.9304
A43: For comparison: STRAIGHT-SIDED frosted 90ct by DDP air from China (alternative to spray-frosting the 8 oz locally)
A44: Plan / SKU | B44: Supplier | C44: Item | D44: Size | E44: Currency | F44: Bottle price | G44: Cap price (per bottle needed) | H44: FX | I44: Goods (CAD/unit) | J44: Frosting (CAD/unit) | K44: Freight & one-time (CAD/unit) | L44: LANDED (CAD/unit) | M44: Landed if US-made (+50% on glass) | N44: Qty | O44: Total (CAD) | P44: Total if US-made (CAD) | Q44: Notes
A45: New B – 90ct | B45: China – Xuzhou Das (frosted 250 ml) | C45: Frosted amber straight-sided 250 ml | D45: 250 ml | E45: USD | F45: ='Frosted Finish – Top 3'!I9 -> 0.55 | G45: ='Frosted Finish – Top 3'!K9 -> 0.07 | H45: =IF(E45="USD",Inputs!$B$10,1) -> 1.424 | I45: =(F45+G45)*H45*(1+Inputs!$B$33) -> 0.88288 | J45: 0 | K45: =Inputs!$B$29/Inputs!$B$7 -> 1.74 | L45: =I45+J45+K45 -> 2.62288 | M45: =L45 -> 2.62288 | N45: =Inputs!$B$7 -> 500 | O45: =L45*N45 -> 1311.44 | P45: =M45*N45 -> 1311.44 | Q45: Same DDP-air route as P3, applied to straight-sided jars.
A46: TOTAL | O46: =SUM(O45:O45) -> 1311.44 | P46: =SUM(P45:P45) -> 1311.44
A48: 3. HEAD-TO-HEAD (all three SKUs, CAD) – best option of each style
A49: Finish | B49: Style | C49: Best plan | E49: Total (CAD) | F49: Total if US-made glass | G49: Avg per unit | H49: Packer saving vs straight-sided
A50: Regular | B50: Straight-sided | C50: Final tab Plan A or B (cheaper) | E50: =MIN('Final Recommendation'!D52,'Final Recommendation'!D53) -> 4411.8237 | F50: =MIN('Final Recommendation'!E52,'Final Recommendation'!E53) -> 4697.12 | G50: =E50/Inputs!$B$8 -> 1.4706079
A51: Regular | B51: Packer | C51: P1 or P2 (cheaper) | E51: =MIN(O20,O27) -> 3451.7237 | F51: =MIN(P20,P27) -> 3451.7237 | G51: =E51/Inputs!$B$8 -> 1.1505746 | H51: =E50-E51 -> 960.10005
A52: Frosted | B52: Straight-sided | C52: Final tab Plan E, or China + DDP-air 90ct | E52: =MIN('Final Recommendation'!D56,'Final Recommendation'!M43+O46) -> 4957.92 | F52: =MIN('Final Recommendation'!E56,'Final Recommendation'!N43+P46) -> 4957.92 | G52: =E52/Inputs!$B$8 -> 1.65264
A53: Frosted | B53: Packer | C53: P3 or P4 (cheaper) | E53: =MIN(O34,O41) -> 3982.48 | F53: =MIN(P34,P41) -> 3982.48 | G53: =E53/Inputs!$B$8 -> 1.3274933 | H53: =E52-E53 -> 975.44
A55: 4. RANKING – cost per bottle (CAD, landed)
A56: Rank | B56: Option | C56: Plan used | E56: Balance (per bottle) | F56: 60ct (per bottle) | G56: 90ct (per bottle) | H56: Avg per bottle | I56: Total (CAD) | J56: Extra per bottle vs #1
A57: 1 | B57: Current bottle (packer) – regular | C57: P1 above | E57: =L17 -> 1.0349647 | F57: =L18 -> 1.2429542 | G57: =L19 -> 1.5206342 | H57: =I57/Inputs!$B$8 -> 1.1505746 | I57: =E57*Inputs!$B$5+F57*Inputs!$B$6+G57*Inputs!$B$7 -> 3451.7237 | J57: =H57-$H$57 -> 0
A58: 2 | B58: Current bottle (packer) – frosted | C58: P3 above | E58: =L31 -> 1.14816 | F58: =L32 -> 1.14816 | G58: =L33 -> 2.22416 | H58: =I58/Inputs!$B$8 -> 1.3274933 | I58: =E58*Inputs!$B$5+F58*Inputs!$B$6+G58*Inputs!$B$7 -> 3982.48 | J58: =H58-$H$57 -> 0.17691877
A59: 3 | B59: Straight-sided – regular | C59: Final tab Plan B (Burch 4+6 oz + cheapest 8 oz) | E59: ='Final Recommendation'!I33 -> 1.3189667 | F59: ='Final Recommendation'!I34 -> 1.59012 | G59: ='Final Recommendation'!K23 -> 1.9576608 | H59: =I59/Inputs!$B$8 -> 1.4706079 | I59: =E59*Inputs!$B$5+F59*Inputs!$B$6+G59*Inputs!$B$7 -> 4411.8237 | J59: =H59-$H$57 -> 0.32003335
A60: 4 | B60: Straight-sided – frosted | C60: China frosted 4+6 oz + 8 oz frosted by DDP air | E60: ='Final Recommendation'!I41 -> 1.41872 | F60: ='Final Recommendation'!I42 -> 1.61808 | G60: =L45 -> 2.62288 | H60: =I60/Inputs!$B$8 -> 1.65264 | I60: =E60*Inputs!$B$5+F60*Inputs!$B$6+G60*Inputs!$B$7 -> 4957.92 | J60: =H60-$H$57 -> 0.50206544
A61: Straight-sided regular rises to ~CAD 1.57/bottle if Burch's jars are US-made (50% surtax). Packer glass from TricorBraun is China-made (no surtax). Website prices + freight estimates: expect ±$0.10–0.20/bottle once quoted; the ranking is unlikely to change.
A63: 5. BEYOND COST
A64: Packer – pros | B64: Cheaper in both finishes. Your manufacturer already fills and seals this style (no line-compatibility risk). Balance keeps its current bottle and label. Regular packers ship all three SKUs together from one North American supplier with China-made glass (no surtax). Only 2 neck/cap/band sizes.
A65: Packer – cons | B65: Not the designer's straight-sided look. 60ct in 150cc is tight if production lands on size 00 (pour-test; 200cc is the fallback but looks < half if size 0). No frosted packers stocked in North America – frosted means China.
A66: Straight-sided – pros | B66: The designer's preferred, more premium look and bigger label panel. 6 oz fits the 60ct at either capsule size.
A67: Straight-sided – cons | B67: Costs more. Manufacturer must confirm their line handles it. Three neck sizes. Many US-distributor jars risk the 50% surtax unless origin is confirmed. Frosted 8 oz for the 90ct is expensive locally.

Sheet Product Links
A1: Product Links – every listing used in the pricing (click to open)
A2: Prices as captured on supplier websites, Oct 9, 2026. Prices change; confirm by quote.
A4: Supplier | B4: Product | C4: Price captured (Oct 9, 2026) | D4: Link
A5: CURRENT BOTTLE STYLE (amber wide-mouth packer) – regular
A6: TricorBraun (US store; glass made in China) | B6: 120cc packer 38-400 (319293) – Balance | C6: $37.63/case of 126 at 18+ cases | D6: https://www.tricorbraun.com/120-cc-amber-glass-round-packer-bottle-38-400-neck-finish.html
A7: TricorBraun | B7: 150cc packer 45-400 (319904) – 60ct | C7: $5.00/case of 12 at 18+ cases | D7: https://www.tricorbraun.com/150-cc-amber-glass-round-packer-bottle-45-400-neck-finish-319904.html
A8: TricorBraun | B8: 200cc packer 45-400 (319906) – 60ct fallback | C8: $6.42/case of 12 at 18+ cases | D8: https://www.tricorbraun.com/200-cc-amber-glass-round-packer-bottle-45-400-neck-finish-319906.html
A9: TricorBraun | B9: 250cc packer 45-400 (319907) – 90ct | C9: $7.34/case of 12 at 18+ cases | D9: https://www.tricorbraun.com/250-cc-amber-glass-round-packer-bottle-45-400-neck-finish.html
A10: TricorBraun | B10: 38-400 black PP cap, F-217 liner (348629) | C10: $261/case of 2,900 | D10: https://www.tricorbraun.com/38-400-black-pp-plastic-continuous-thread-closure-f-217-liner.html
A11: TricorBraun | B11: 45-400 black PP cap (HS-035 liner) | C11: ~$0.10–0.12 each in 2,000-pc case | D11: https://www.tricorbraun.com/45-400-black-pp-plastic-continuous-thread-lined-closure-hs-035-liner.html
A12: Containers & Packaging Supply | B12: 120cc packer G18118AM | C12: $0.39 full case | D12: https://www.containerandpackaging.com/products/glass-packer-bottle/g18118am/
A13: Containers & Packaging Supply | B13: 150cc packer G18117AM | C13: $0.43 full case | D13: https://www.containerandpackaging.com/products/glass-packer-bottle/g18117am/
A14: Containers & Packaging Supply | B14: 200cc packer G18119AM | C14: $0.47 full case | D14: https://www.containerandpackaging.com/products/glass-packer-bottle/g18119am/
A15: SKS Bottle | B15: 120cc pharmaceutical round (packer) 40110120.01M | C15: $45.31/96 on special; free UPS to Ontario on US$500+ | D15: https://www.sks-bottle.com/340c/fin7552.html
A16: Bottlestore | B16: 120cc amber packer | C16: $0.49 | D16: https://www.bottlestore.com/120cc-amber-wide-mouth-packer-round-glass-bottle-38-405-neck.html
A17: Bottlestore | B17: 150cc amber packer | C17: $0.42 | D17: https://www.bottlestore.com/150cc-amber-glass-wide-mouth-round-packer-bottle-round-45-400-neck.html
... A24: China – NOVA | B24: Amber packer 100–300ml with screw cap | C24: US$0.058–0.15 at 1,000 | D24: https://nuohuabaozhuang.en.made-in-china.com/product/OTpRyhFDrKYW/China-Wholesale-100ml-120ml-150ml-200ml-250ml-300ml-Amber-Wide-Mouth-Pharmaceutical-Grade-Glass-Bottle-with-Screw-Cap-for-Pills.html
A25: CURRENT BOTTLE STYLE – frosted (China only; none stocked in North America)
A26: China – Jinan Snail | B26: Frosted amber wide-mouth pill bottle | C26: US$0.30 at 1,000–9,999 | D26: https://snailglass.en.made-in-china.com/product/iJIRHfKEItpO/China-Wholesale-Amber-Frosted-Empty-Wide-Mouth-Glass-Bottle-Medicine-Pill-Bottles.html
A27: China – Jinan Snail | B27: Frosted 100–250ml health/capsule bottle | C27: US$0.30 | D27: https://snailglass.en.made-in-china.com/product/MxEYkSFGJRrb/China-100ml-120ml-150ml-250ml-Frosted-Glass-Health-Bottle-Capsule-with-Screw-Lid.html
A28: China – Advantrio | B28: Frosted amber 120ml pill bottle (MOQ 500) | C28: Quote | D28: https://advantriopackaging.en.made-in-china.com/product/RtXYDOaMZBUC/China-Wholesale-Empty-Wide-Mouth-Amber-Frosted-Glass-Jar-Pill-Capsule-Bottle-120ml.html
A29: China – Advantrio | B29: Frosted 200ml pill bottle (MOQ 500) | C29: Quote | D29: https://advantriopackaging.en.made-in-china.com/product/uASYIkaDhBRw/China-Luxury-Custom-Wide-Mouth-200ml-Frosted-Glass-Pill-Bottle-Jar-with-Lid.html
A30: STRAIGHT-SIDED JARS – regular
A31: Burch Bottle | B31: 4 oz amber straight-sided 58-400 (1SSA042GHG) | C31: $11.45/24 at 50–299 cs | D31: https://www.burchbottle.com/4oz-Amber-Straight-Sided-Jar-58-400
A32: Burch Bottle | B32: 6 oz amber straight-sided 63-400 (1SSA062GHG) | C32: $8.13/12 base | D32: https://www.burchbottle.com/6oz-Amber-Straight-Sided-Jar-63-400
A33: Burch Bottle | B33: 9 oz amber straight-sided 70-400 (1SSA092SGC) | C33: $5.29/12 at 40–175 cs | D33: https://www.burchbottle.com/9oz-Amber-Straight-Sided-Jar-70-400
A34: Burch Bottle | B34: 70-400 black PP cap PS22 (2BP0706MR) | C34: $0.30 | D34: https://www.burchbottle.com/70-400-Black-Polypropylene-RM-Ps22-Print-F217-Lined-Cap
A35: Fillmore Container | B35: 4 oz amber straight-sided (R04-30C) | C35: $12.95/24 | D35: https://www.fillmorecontainer.com/r04-30c-case24ct-1-12oz.html
A36: Fillmore Container | B36: 6 oz amber straight-sided (B06-30C) | C36: $7.99/12 | D36: https://www.fillmorecontainer.com/6-oz-amber-straight-sided-jar-case-of-12.html
A37: Fillmore Container | B37: 9 oz amber straight-sided (B09-30C) | C37: $6.35/12 | D37: https://www.fillmorecontainer.com/9-oz-amber-straight-sided-jar.html
A38: Containers & Packaging Supply | B38: 4 oz straight-sided G850AM | C38: $0.45 | D38: https://www.containerandpackaging.com/products/glass-straight-sided-jar/g850am/
A39: Containers & Packaging Supply | B39: 6 oz straight-sided G506AM | C39: $0.57 at 500 | D39: https://www.containerandpackaging.com/products/glass-straight-sided-jar/G506AM/
A40: SKS Bottle | B40: 8 oz amber straight-sided 70/400 (40530080.03S) – 90ct | C40: $31.68/36 | D40: https://www.sks-bottle.com/product/305037.html
A41: SKS Bottle | B41: 70/400 black cap, foam induction liner (2101-79) | C41: $159.60/760 | D41: https://www.sks-bottle.com/product/10710.html
A42: SKS Bottle | B42: Free shipping policy (Canada) | C42: US$500+ to Ontario | D42: https://www.sks-bottle.com/info/free_shipping.html
... A53: China – Xuzhou Selead | B53: Amber straight-sided 2/4/6/8 oz | C53: US$0.20–0.80, MOQ 5,000 | D53: https://xzselead.en.made-in-china.com/product/GamrQSoWqUcX/China-2oz-4oz-6oz-8oz-Amber-Glass-Jar-Straight-Sided-Glass-Candle-Jar-with-Metal-Lid-Clear-Amber-Glass-Storage-Jar-Candle-Holder.html
A54: STRAIGHT-SIDED JARS – frosted
A55: China – Xuzhou Das | B55: Frosted amber straight-sided 2/4/8 oz | C55: US$0.41 at 2,000+ | D55: https://daspacking.en.made-in-china.com/product/CdRGEuVYJmpN/China-Wholesale-2oz-4oz-8oz-60g-120g-250g-Frosted-Clear-Amber-Airtight-Straight-Sided-Round-Face-Cosmetic-Cream-Candle-Glass-Jar-and-Container-with-Lids.html
A56: The Bottle Depot (designer's link) | B56: 4 oz amber frosted straight-sided (frosted only up to 4 oz) | C56: $77.14/90 (sold out) | D56: https://thebottledepot.co/products/4-oz-amber-frosted-glass-straight-sided-round-jar-58-400-neck-finish
A57: Liquid Bottles | B57: 9 oz frosted amber straight-sided (out of stock) | C57: $1.57 | D57: https://www.liquidbottles.com/products/4738/9oz-Frosted-Amber-Glass-Jar-70-400-Neck-Finish-72cs
A58: Stanpac (Ontario) | B58: Spray-frost decorating (quote only) | C58: Quote | D58: https://www.stanpacnet.com/glass-container-printing/
A59: SHRINK BANDS (tamper seal)
A60: Uline Canada | B60: Clear perforated shrink bands (38–70 mm) | C60: CAD 21–26 per 1,000 | D60: https://www.uline.ca/BL_2410/Clear-Shrink-Bands
A61: SKS Bottle | B61: Shrink bands | C61: ~US$0.02 each | D61: https://www.sks-bottle.com/340c/fin6484.html
A62: DUTY, SURTAX & FREIGHT SOURCES
A63: CBSA | B63: Customs Tariff 2026, chapter 70 (7010.90.00 MFN Free) | C63: — | D63: https://www.cbsa-asfc.gc.ca/trade-commerce/tariff-tarif/2026/01-99/ch70-2026-eng.pdf
A64: Canada Gazette | B64: United States Surtax Order (2026), SOR/2026-186 (50% on 7010.90.00) | C64: — | D64: https://gazette.gc.ca/rp-pr/p2/2026/2026-09-23/html/sor-dors186-eng.html
A65: CBSA | B65: Customs Notice 26-23 | C65: — | D65: https://www.cbsa-asfc.gc.ca/publications/cn-ad/cn26-23-eng.html
A66: Justice Laws | B66: US Surtax Remission Order (possible refund) | C66: — | D66: https://laws-lois.justice.gc.ca/eng/regulations/SOR-2025-122/FullText.html
A67: Sino Shipping | B67: China → Canada LCL rates | C67: US$190/m³ | D67: https://www.sino-shipping.com/country-guides/shipping-from-china-to-canada/
A68: ddpchain | B68: China → Canada DDP sea/air per kg | C68: CAD 2.85/kg sea; 8.74/kg air | D68: https://ddpchain.com/canada/
A69: Clearit | B69: Customs brokerage fees | C69: CAD 84.95 + 5% | D69: https://clearit.ca/l/customs-broker
A70: Warp | B70: US LTL rate benchmarks | C70: 500 lb pallet avg US$579 | D70: https://wearewarp.com/research/ltl-rate-benchmarks

Sheet Summary
A1: Cocoon Supplements – Amber Straight-Sided Jar Sourcing
A2: Prepared by the procurement agent, updated Oct 9, 2026. Landed cost = jar + cap + freight, brokerage and one-time costs, in CAD per unit. Order: Balance 2,000 · new 60ct 500 · new 90ct 500 (edit on Inputs).
A3: ⚠ CONFIRMED: Canada charges a 50% surtax on US-MADE glass jars since Sept 8, 2026 (SOR/2026-186, tariff 7010.90.00). It applies by where the jar was made, not where it ships from. Ask US suppliers for country of origin. Both cases are shown below.
A5: Benchmark (bottle + lid, CAD/unit) | D5: =Inputs!$B$15 -> 3.44 | E5: Implied max from the previous manufacturer's $3.74 all-in quote minus the $0.30 label. Enter your current manufacturer's figure on Inputs.
A7: REGULAR (glossy) – Top 3 single-source options (all three SKUs from one supplier)
A8: Rank | B8: Option | C8: Jar sizes (30 / 60 / 90 ct) | D8: Landed CAD/unit | E8: Landed if US-made (surtax) | F8: Total all SKUs (CAD) | G8: Lead time | H8: Key pros | I8: Key risks / flags
A9: #1 | B9: Burch Bottle & Packaging (US) | C9: 4 oz / 6 oz / 9 oz | D9: ='Regular Finish – Top 3'!P10 -> 1.2893022 | E9: ='Regular Finish – Top 3'!S10 -> 1.6484667 | F9: ='Regular Finish – Top 3'!Q10 -> 3867.9067 | G9: ~1–2 wks + freight | H9: Lowest local cost; true 6 oz; deep stock; PS22 tamper-evident cap option | I9: Origin unknown (surtax risk); confirm 9 oz colour; USD/FX
A10: #2 | B10: Fillmore Container (US) | C10: 4 oz / 6 oz / 9 oz | D10: ='Regular Finish – Top 3'!P19 -> 1.3810711 | E10: ='Regular Finish – Top 3'!S19 -> 1.779 | F10: ='Regular Finish – Top 3'!Q19 -> 4143.2133 | G10: ~1–2 wks + freight | H10: Confirms shipping to Canada; same 4/6/9 line | I10: ~10% dearer than Burch; origin unknown (surtax risk)
A11: #3 | B11: China direct factory | C11: 120 / 180–190 / 250–270 ml | D11: ='Regular Finish – Top 3'!P28 -> 1.3286667 | E11: ='Regular Finish – Top 3'!S28 -> 1.3286667 | F11: ='Regular Finish – Top 3'!Q28 -> 3986 | G11: 10–13 weeks | H11: Cheapest; no surtax; duty Free | I11: Too slow for the urgent launch; RFQ + samples + QC needed; neck matching
A13: FROSTED / MATTE – Top 3 single-source options
A14: Rank | B14: Option | C14: Jar sizes (30 / 60 / 90 ct) | D14: Landed CAD/unit | E14: Landed if US-made (surtax) | F14: Total all SKUs (CAD) | G14: Lead time | H14: Key pros | I14: Key risks / flags
A15: #1 | B15: China direct factory (frosted) | C15: 120 / 180–190 / 250–270 ml | D15: ='Frosted Finish – Top 3'!P10 -> 1.4259733 | E15: ='Frosted Finish – Top 3'!S10 -> 1.4259733 | F15: ='Frosted Finish – Top 3'!Q10 -> 4277.92 | G15: 10–13 weeks | H15: Far cheapest; true etched frost; no surtax | I15: Too slow for the urgent launch; 180–190 ml frosted needs RFQ; QC risk
A16: #2 | B16: Burch + Canadian spray-frost | C16: 4 oz / 6 oz / 9 oz | D16: ='Frosted Finish – Top 3'!P19 -> 2.4893022 | E16: ='Frosted Finish – Top 3'!S19 -> 2.8484667 | F16: ='Frosted Finish – Top 3'!Q19 -> 7467.9067 | G16: ~3–6 weeks | H16: North American; true 6 oz; frost done in Canada | I16: Frost cost is an estimate; spray can scuff; surtax risk on jars
A17: #3 | B17: Fillmore + Canadian spray-frost | C17: 4 oz / 6 oz / 9 oz | D17: ='Frosted Finish – Top 3'!P28 -> 2.5810711 | E17: ='Frosted Finish – Top 3'!S28 -> 2.979 | F17: ='Frosted Finish – Top 3'!Q28 -> 7743.2133 | G17: ~3–6 weeks | H17: As #2; Fillmore ships to Canada | I17: Slightly dearer than #2; same risks
A19: SPLIT PLAN – one launch SKU bought locally now, the other two from China (details on 'Split Plan' sheet)
A20: Plan | B20: Description | D20: Total (CAD) | E20: Total if US-made | F20: vs all-local | G20: vs all-local (surtax)
A21: R-A | B21: ='Split Plan – Local vs China'!B6 -> Regular – all local (Burch; 90ct jar size guessed now) | D21: ='Split Plan – Local vs China'!C6 -> 3867.9067 | E21: ='Split Plan – Local vs China'!E6 -> 4945.4 | F21: ='Split Plan – Local vs China'!D6 -> 0 | G21: ='Split Plan – Local vs China'!F6 -> 0
A22: R-B1 | B22: ='Split Plan – Local vs China'!B7 -> Regular – FLEX: 6 oz local; 90ct is size 00 → 60ct launches | D22: ='Split Plan – Local vs China'!C7 -> 4693.94 | E22: ='Split Plan – Local vs China'!E7 -> 4935.13 | F22: ='Split Plan – Local vs China'!D7 -> 826.03333 | G22: ='Split Plan – Local vs China'!F7 -> -10.27
A23: R-FX0 | B23: ='Split Plan – Local vs China'!B8 -> Regular – FLEX: 6 oz local; 90ct is size 0 → 90ct launches | D23: ='Split Plan – Local vs China'!C8 -> 4716.66 | E23: ='Split Plan – Local vs China'!E8 -> 4957.85 | F23: ='Split Plan – Local vs China'!D8 -> 848.75333 | G23: ='Split Plan – Local vs China'!F8 -> 12.45
A24: R-B2 | B24: ='Split Plan – Local vs China'!B9 -> Regular – 90ct local (Burch 9 oz), rest China | D24: ='Split Plan – Local vs China'!C9 -> 4576.6333 | E24: ='Split Plan – Local vs China'!E9 -> 4733.57 | F24: ='Split Plan – Local vs China'!D9 -> 708.72667 | G24: ='Split Plan – Local vs China'!F9 -> -211.83
A25: R-B2c | B25: ='Split Plan – Local vs China'!B10 -> Regular – 90ct local (Richards, Canada), rest China | D25: ='Split Plan – Local vs China'!C10 -> 4217.12 | E25: ='Split Plan – Local vs China'!E10 -> 4217.12 | F25: ='Split Plan – Local vs China'!D10 -> 349.21333 | G25: ='Split Plan – Local vs China'!F10 -> -728.28
A26: F-A | B26: ='Split Plan – Local vs China'!B12 -> Frosted – all local (Burch + spray frost) | D26: ='Split Plan – Local vs China'!C12 -> 7467.9067 | E26: ='Split Plan – Local vs China'!E12 -> 8545.4 | F26: ='Split Plan – Local vs China'!D12 -> 0 | G26: ='Split Plan – Local vs China'!F12 -> 0
A27: F-B1 | B27: ='Split Plan – Local vs China'!B13 -> Frosted – FLEX: 6 oz local; 90ct is size 00 → 60ct launches | D27: ='Split Plan – Local vs China'!C13 -> 6075.42 | E27: ='Split Plan – Local vs China'!E13 -> 6316.61 | F27: ='Split Plan – Local vs China'!D13 -> -1392.4867 | G27: ='Split Plan – Local vs China'!F13 -> -2228.79
A28: F-FX0 | B28: ='Split Plan – Local vs China'!B14 -> Frosted – FLEX: 6 oz local; 90ct is size 0 → 90ct launches | D28: ='Split Plan – Local vs China'!C14 -> 6091.02 | E28: ='Split Plan – Local vs China'!E14 -> 6332.21 | F28: ='Split Plan – Local vs China'!D14 -> -1376.8867 | G28: ='Split Plan – Local vs China'!F14 -> -2213.19
A29: F-B2 | B29: ='Split Plan – Local vs China'!B15 -> Frosted – 90ct local (Burch 9 oz + spray frost), rest China | D29: ='Split Plan – Local vs China'!C15 -> 5950.9933 | E29: ='Split Plan – Local vs China'!E15 -> 6107.93 | F29: ='Split Plan – Local vs China'!D15 -> -1516.9133 | G29: ='Split Plan – Local vs China'!F15 -> -2437.47
A30: F-B2s | B30: ='Split Plan – Local vs China'!B16 -> Frosted – 90ct local (Liquid Bottles stock), rest China | D30: ='Split Plan – Local vs China'!C16 -> 5679.64 | E30: ='Split Plan – Local vs China'!E16 -> 6238.56 | F30: ='Split Plan – Local vs China'!D16 -> -1788.2667 | G30: ='Split Plan – Local vs China'!F16 -> -2306.84
A32: Recommendation (on current estimates – verify with quotes)
A33: FINAL RECOMMENDATION: see the 'Final Recommendation' tab (first tab).
A34: • Launch the 90ct androgen-balancing product first, in an 8 oz amber straight-sided jar bought locally (500 units; cheapest landed: SKS).
A35: • Balance (4 oz) + 60ct liver booster (6 oz): buy both from Burch in one shipment if Burch's jars aren't US-made; if they are (50% surtax), a China order is cheaper.
A36: • The tables above are the option analysis that led there.

Sheet Inputs
A1: Inputs & Assumptions
A2: Blue text on yellow = editable input. Every other sheet recalculates from these cells. Replace estimates with real quotes as they arrive.
A4: ORDER & BENCHMARK
A5: Units – Balance 30ct (4 oz) | B5: 2000 | C5: Owner: ~2,000 per run for the existing product. ASSUMED unchanged – edit if needed.
A6: Units – New 60ct liver booster (6 oz) | B6: 500 | C6: Owner: manufacturer can go as low as 500 per new SKU.
A7: Units – New 90ct androgen product (8 oz) | B7: 500 | C7: Owner: manufacturer can go as low as 500 per new SKU.
A8: Total units | B8: =$B$5+$B$6+$B$7 -> 3000 | C8: Sum of the three SKUs.
A9: Number of SKUs | B9: 3 | C9: Balance (30x size 0) + new 60ct + new 90ct.
A10: USD → CAD exchange rate | B10: 1.424 | C10: Bank of Canada rate, Oct 8, 2026. Update to your bank's rate on order day.
A11: Previous manufacturer – all-in packaging quote (CAD/unit) | B11: 3.74 | C11: From owner: bottle + lid + label + seal + bubble wrap. Currency assumed CAD.
A12: Estimated label cost (CAD/unit) | B12: 0.3 | C12: From owner's estimate.
A13: Implied MAX bottle + lid benchmark (CAD/unit) | B13: =$B$11-$B$12 -> 3.44 | C13: Upper bound only – the $3.74 also includes seal + bubble wrap, so true bottle + lid cost is lower.
A14: Current manufacturer bottle + lid cost (CAD/unit) – TO CONFIRM | C14: Fill in once your current manufacturer confirms. Leave blank to use the implied max above.
A15: Benchmark used in comparisons (CAD/unit) | B15: =IF($B$14="",$B$13,$B$14) -> 3.44 | C15: Uses the confirmed figure if entered, else the implied max.
A17: FREIGHT – ONE SHIPMENT FOR ALL THREE SKUs (~3,000 jars)
A18: US → Canada LTL, all SKUs in one shipment (~1 pallet, 900–1,100 lb) (USD) | B18: 650 | C18: ESTIMATE: Warp LTL index (Oct 9, 2026) – 500 lb US domestic pallet avg US$579 (middle half $390–694); cross-border costs more. Get a quote to your postal code.
A19: Customs brokerage, US import (CAD) | B19: 175 | C19: ESTIMATE: CAD 80–250. CPS includes brokerage in its online UPS rate.
A20: Domestic Canada freight, ~1 pallet (CAD) | B20: 300 | C20: ESTIMATE: Freightera Ontario pallet samples CAD 74–135 (2020–22) plus growth; Uline/Richards show cost at checkout.
A21: China → your door, LCL all three SKUs (~1.6 m³, ~550 kg) (CAD) | B21: 1250 | C21: ESTIMATE from live forwarder rates (Oct 2026): LCL US$150–220/m³ (1 m³ minimum) + CFS/THC + docs + brokerage (Clearit CAD 84.95 + 5%) + delivery.
A23: FREIGHT – SMALL / SPLIT SHIPMENTS
A24: US → Canada, ONE SKU of ~500 jars (200–360 lb; courier or partial pallet) (USD) | B24: 400 | C24: ESTIMATE: US$300–700. Exception: SKS ships free UPS Ground to Ontario on US$500+ orders (used on the Final tab).
A25: Customs brokerage, small US import (CAD) | B25: 125 | C25: ESTIMATE: CAD 80–250.
A26: Domestic Canada freight, ONE SKU of ~500 jars (CAD) | B26: 150 | C26: ESTIMATE: CAD 75–250.
A27: China → your door, LCL Balance 4 oz + 90ct 8 oz (~1.2 m³) (CAD) | B27: 1080 | C27: ESTIMATE from live rates (range CAD 550–1,600).
A28: China → your door, LCL Balance 4 oz + 60ct 6 oz (~1.0–1.3 m³, 350–450 kg) (CAD) | B28: 1060 | C28: ESTIMATE, mid case from live rates (range CAD 550–1,575). Balance alone ≈ CAD 1,015: adding the 60ct costs only ~CAD 35–110 because of the 1 m³ minimum.
A29: China → your door by DDP AIR, ONE SKU of ~500 bottles (~75–100 kg) (CAD) | B29: 870 | C29: ESTIMATE: ddpchain DDP air ~CAD 8.74/kg; 7–12 days transit after production. Lets a China-made launch SKU arrive in ~5–7 weeks.
A30: China samples + courier + wire fees + light QC (CAD, one-time) | B30: 600 | C30: ESTIMATE: CAD 250–900.
A32: DUTY & SURTAX
A33: Import duty, glass jars HS 7010.90 (MFN – applies to China and US) | B33: 0 | C33: VERIFIED: CBSA Customs Tariff T2026 ch. 70 (incl. T2026-2, Sept 1, 2026): 7010.90.00 MFN Free. No China surtax and no anti-dumping measure on glass jars.
A34: Canadian surtax on US-MADE glass jars (jar value only) | B34: 0.5 | C34: VERIFIED: United States Surtax Order (2026), SOR/2026-186, Schedule 3 (50%) lists 7010.90.00; in force Sept 8, 2026 (CBSA Customs Notice 26-23). Applies to goods ORIGINATING in the US, wherever shipped from. Plastic caps (3923.50) are not listed. A remission order may refund it for goods used in Canadian manufacturing – ask a broker; plan as if payable.
A36: FROSTING / DECORATION (estimates – quote required)
A37: North American spray-frost per jar (CAD) | B37: 0.45 | C37: ESTIMATE: CAD 0.30–0.60/jar. Stanpac (Smithville ON): spray frost, no minimum but economical at ~1 pallet, 3–5 weeks; no published price – quote required.
A38: North American spray-frost setup per SKU (CAD) | B38: 650 | C38: ESTIMATE: CAD 300–1,000 per SKU.
A39: Freight to/from decorator (CAD) | B39: 300 | C39: ESTIMATE.

Sheet Capsule Sizing
A1: Capsule Fill Sizing – which jar fits each SKU and looks at least half full?
A2: Volume needed depends on the capsules, not the container shape. A straight-sided jar needs the same cc as a packer bottle; it's just shorter and wider. In a straight-sided jar the fill line rises evenly, so 'pile %' ≈ how full it looks.
A4: Capsule specs
A5: Capsule size | B5: Closed length (mm) | C5: Outer diameter (mm) | D5: Envelope volume per capsule (cc) | E5: Pile volume per capsule – capsules only (cc) | F5: Space needed per capsule incl. headspace (cc)
A6: 0 | B6: 21.7 | C6: 7.65 | D6: =(PI()*(C6/2)^2*(B6-C6)+4/3*PI()*(C6/2)^3)/1000 -> 0.88020034 | E6: =D6/$B$10 -> 1.6003642 | F6: =E6*(1+$B$11) -> 1.8404189
A7: 00 | B7: 23.3 | C7: 8.53 | D7: =(PI()*(C7/2)^2*(B7-C7)+4/3*PI()*(C7/2)^3)/1000 -> 1.1690223 | E7: =D7/$B$10 -> 2.1254952 | F7: =E7*(1+$B$11) -> 2.4443194
A9: Assumptions
A10: Packing fraction (share of space filled by randomly poured capsules) | B10: 0.55 | C10: Random-packing estimate for capsule shapes. Calibrated to industry bottle charts (60x0 → 120cc, 90x0 → 175cc).
A11: Headspace allowance | B11: 0.15 | C11: Room for cotton/desiccant and so the cap closes without crushing capsules.
A12: Owner rule: minimum visible fill | B12: 0.5 | C12: From owner: no jar may look less than half full.
A13: Max space used before 'tight' | B13: 0.9
A15: Jar capacities (nominal)
A16: Jar | B16: Capacity (ml) | C16: Neck finish
A17: 4 oz | B17: 118 | C17: 58-400 | D17: Nominal (label) capacity. Brim-full capacity is typically 10–15% higher, so the 'space used' results are conservative and the 'looks full' results are slightly generous.
A18: 6 oz | B18: 177 | C18: 63-400
A19: 190 ml (China) | B19: 190 | C19: ~63 mm
A20: 8 oz | B20: 237 | C20: 70-400
A21: 250 ml (China) | B21: 250 | C21: ~70 mm
A22: 9 oz | B22: 266 | C22: 70-400
A24: How full will it LOOK? (capsule pile ÷ jar capacity; red = below the half-full rule)
A25: SKU / scenario | B25: Capsule size | C25: Count | D25: Pile (cc) | E25: Needed incl. headspace (cc) | F25: 4 oz | G25: 6 oz | H25: 190 ml (China) | I25: 8 oz | J25: 250 ml (China) | K25: 9 oz
A26: Balance – 30ct (current) | B26: 0 | C26: 30 | D26: =C26*INDEX($E$6:$E$7,MATCH(B26,$A$6:$A$7,0)) -> 48.010927 | E26: =C26*INDEX($F$6:$F$7,MATCH(B26,$A$6:$A$7,0)) -> 55.212567 | F26: =$D26/$B$17 -> 0.40687227 | G26: =$D26/$B$18 -> 0.27124818 | H26: =$D26/$B$19 -> 0.25268909 | I26: =$D26/$B$20 -> 0.20257775 | J26: =$D26/$B$21 -> 0.19204371 | K26: =$D26/$B$22 -> 0.18049221
A27: New A – 60ct (if size 00) | B27: 00 | C27: 60 | D27: =C27*INDEX($E$6:$E$7,MATCH(B27,$A$6:$A$7,0)) -> 127.52971 | E27: =C27*INDEX($F$6:$F$7,MATCH(B27,$A$6:$A$7,0)) -> 146.65917 | F27: =$D27/$B$17 -> 1.0807603 | G27: =$D27/$B$18 -> 0.72050684 | H27: =$D27/$B$19 -> 0.671209 | I27: =$D27/$B$20 -> 0.53810004 | J27: =$D27/$B$21 -> 0.51011884 | K27: =$D27/$B$22 -> 0.479435
A28: New A – 60ct (if size 0) | B28: 0 | C28: 60 | D28: =C28*INDEX($E$6:$E$7,MATCH(B28,$A$6:$A$7,0)) -> 96.021855 | E28: =C28*INDEX($F$6:$F$7,MATCH(B28,$A$6:$A$7,0)) -> 110.42513 | F28: =$D28/$B$17 -> 0.81374453 | G28: =$D28/$B$18 -> 0.54249635 | H28: =$D28/$B$19 -> 0.50537818 | I28: =$D28/$B$20 -> 0.40515551 | J28: =$D28/$B$21 -> 0.38408742 | K28: =$D28/$B$22 -> 0.36098442
A29: New B – 90ct (if size 00) | B29: 00 | C29: 90 | D29: =C29*INDEX($E$6:$E$7,MATCH(B29,$A$6:$A$7,0)) -> 191.29457 | E29: =C29*INDEX($F$6:$F$7,MATCH(B29,$A$6:$A$7,0)) -> 219.98875 | F29: =$D29/$B$17 -> 1.6211404 | G29: =$D29/$B$18 -> 1.0807603 | H29: =$D29/$B$19 -> 1.0068135 | I29: =$D29/$B$20 -> 0.80715007 | J29: =$D29/$B$21 -> 0.76517826 | K29: =$D29/$B$22 -> 0.7191525
A30: New B – 90ct (if size 0) | B30: 0 | C30: 90 | D30: =C30*INDEX($E$6:$E$7,MATCH(B30,$A$6:$A$7,0)) -> 144.03278 | E30: =C30*INDEX($F$6:$F$7,MATCH(B30,$A$6:$A$7,0)) -> 165.6377 | F30: =$D30/$B$17 -> 1.2206168 | G30: =$D30/$B$18 -> 0.81374453 | H30: =$D30/$B$19 -> 0.75806727 | I30: =$D30/$B$20 -> 0.60773326 | J30: =$D30/$B$21 -> 0.57613113 | K30: =$D30/$B$22 -> 0.54147662
A32: Verdict per jar (OK · Tight – test · Looks < half · Too small)
A33: SKU / scenario | B33: Capsule size | C33: Count | D33: Pile (cc) | E33: Needed incl. headspace (cc) | F33: 4 oz | G33: 6 oz | H33: 190 ml (China) | I33: 8 oz | J33: 250 ml (China) | K33: 9 oz
A34: Balance – 30ct (current) | B34: 0 | C34: 30 | D34: =C34*INDEX($E$6:$E$7,MATCH(B34,$A$6:$A$7,0)) -> 48.010927 | E34: =C34*INDEX($F$6:$F$7,MATCH(B34,$A$6:$A$7,0)) -> 55.212567 | F34: =IF($E34/$B$17>1,"Too small",IF($D34/$B$17<$B$12,"Looks < half",IF($E34/$B$17>$B$13,"Tight – test","OK"))) -> Looks < half | G34: =IF($E34/$B$18>1,"Too small",IF($D34/$B$18<$B$12,"Looks < half",IF($E34/$B$18>$B$13,"Tight – test","OK"))) -> Looks < half | H34: =IF($E34/$B$19>1,"Too small",IF($D34/$B$19<$B$12,"Looks < half",IF($E34/$B$19>$B$13,"Tight – test","OK"))) -> Looks < half | I34: =IF($E34/$B$20>1,"Too small",IF($D34/$B$20<$B$12,"Looks < half",IF($E34/$B$20>$B$13,"Tight – test","OK"))) -> Looks < half | J34: =IF($E34/$B$21>1,"Too small",IF($D34/$B$21<$B$12,"Looks < half",IF($E34/$B$21>$B$13,"Tight – test","OK"))) -> Looks < half | K34: =IF($E34/$B$22>1,"Too small",IF($D34/$B$22<$B$12,"Looks < half",IF($E34/$B$22>$B$13,"Tight – test","OK"))) -> Looks < half
A35: New A – 60ct (if size 00) | B35: 00 | C35: 60 | D35: =C35*INDEX($E$6:$E$7,MATCH(B35,$A$6:$A$7,0)) -> 127.52971 | E35: =C35*INDEX($F$6:$F$7,MATCH(B35,$A$6:$A$7,0)) -> 146.65917 | F35: =IF($E35/$B$17>1,"Too small",IF($D35/$B$17<$B$12,"Looks < half",IF($E35/$B$17>$B$13,"Tight – test","OK"))) -> Too small | G35: =IF($E35/$B$18>1,"Too small",IF($D35/$B$18<$B$12,"Looks < half",IF($E35/$B$18>$B$13,"Tight – test","OK"))) -> OK | H35: =IF($E35/$B$19>1,"Too small",IF($D35/$B$19<$B$12,"Looks < half",IF($E35/$B$19>$B$13,"Tight – test","OK"))) -> OK | I35: =IF($E35/$B$20>1,"Too small",IF($D35/$B$20<$B$12,"Looks < half",IF($E35/$B$20>$B$13,"Tight – test","OK"))) -> OK | J35: =IF($E35/$B$21>1,"Too small",IF($D35/$B$21<$B$12,"Looks < half",IF($E35/$B$21>$B$13,"Tight – test","OK"))) -> OK | K35: =IF($E35/$B$22>1,"Too small",IF($D35/$B$22<$B$12,"Looks < half",IF($E35/$B$22>$B$13,"Tight – test","OK"))) -> Looks < half
A36: New A – 60ct (if size 0) | B36: 0 | C36: 60 | D36: =C36*INDEX($E$6:$E$7,MATCH(B36,$A$6:$A$7,0)) -> 96.021855 | E36: =C36*INDEX($F$6:$F$7,MATCH(B36,$A$6:$A$7,0)) -> 110.42513 | F36: =IF($E36/$B$17>1,"Too small",IF($D36/$B$17<$B$12,"Looks < half",IF($E36/$B$17>$B$13,"Tight – test","OK"))) -> Tight – test | G36: =IF($E36/$B$18>1,"Too small",IF($D36/$B$18<$B$12,"Looks < half",IF($E36/$B$18>$B$13,"Tight – test","OK"))) -> OK | H36: =IF($E36/$B$19>1,"Too small",IF($D36/$B$19<$B$12,"Looks < half",IF($E36/$B$19>$B$13,"Tight – test","OK"))) -> OK | I36: =IF($E36/$B$20>1,"Too small",IF($D36/$B$20<$B$12,"Looks < half",IF($E36/$B$20>$B$13,"Tight – test","OK"))) -> Looks < half | J36: =IF($E36/$B$21>1,"Too small",IF($D36/$B$21<$B$12,"Looks < half",IF($E36/$B$21>$B$13,"Tight – test","OK"))) -> Looks < half | K36: =IF($E36/$B$22>1,"Too small",IF($D36/$B$22<$B$12,"Looks < half",IF($E36/$B$22>$B$13,"Tight – test","OK"))) -> Looks < half
A37: New B – 90ct (if size 00) | B37: 00 | C37: 90 | D37: =C37*INDEX($E$6:$E$7,MATCH(B37,$A$6:$A$7,0)) -> 191.29457 | E37: =C37*INDEX($F$6:$F$7,MATCH(B37,$A$6:$A$7,0)) -> 219.98875 | F37: =IF($E37/$B$17>1,"Too small",IF($D37/$B$17<$B$12,"Looks < half",IF($E37/$B$17>$B$13,"Tight – test","OK"))) -> Too small | G37: =IF($E37/$B$18>1,"Too small",IF($D37/$B$18<$B$12,"Looks < half",IF($E37/$B$18>$B$13,"Tight – test","OK"))) -> Too small | H37: =IF($E37/$B$19>1,"Too small",IF($D37/$B$19<$B$12,"Looks < half",IF($E37/$B$19>$B$13,"Tight – test","OK"))) -> Too small | I37: =IF($E37/$B$20>1,"Too small",IF($D37/$B$20<$B$12,"Looks < half",IF($E37/$B$20>$B$13,"Tight – test","OK"))) -> Tight – test | J37: =IF($E37/$B$21>1,"Too small",IF($D37/$B$21<$B$12,"Looks < half",IF($E37/$B$21>$B$13,"Tight – test","OK"))) -> OK | K37: =IF($E37/$B$22>1,"Too small",IF($D37/$B$22<$B$12,"Looks < half",IF($E37/$B$22>$B$13,"Tight – test","OK"))) -> OK
A38: New B – 90ct (if size 0) | B38: 0 | C38: 90 | D38: =C38*INDEX($E$6:$E$7,MATCH(B38,$A$6:$A$7,0)) -> 144.03278 | E38: =C38*INDEX($F$6:$F$7,MATCH(B38,$A$6:$A$7,0)) -> 165.6377 | F38: =IF($E38/$B$17>1,"Too small",IF($D38/$B$17<$B$12,"Looks < half",IF($E38/$B$17>$B$13,"Tight – test","OK"))) -> Too small | G38: =IF($E38/$B$18>1,"Too small",IF($D38/$B$18<$B$12,"Looks < half",IF($E38/$B$18>$B$13,"Tight – test","OK"))) -> Tight – test | H38: =IF($E38/$B$19>1,"Too small",IF($D38/$B$19<$B$12,"Looks < half",IF($E38/$B$19>$B$13,"Tight – test","OK"))) -> OK | I38: =IF($E38/$B$20>1,"Too small",IF($D38/$B$20<$B$12,"Looks < half",IF($E38/$B$20>$B$13,"Tight – test","OK"))) -> OK | J38: =IF($E38/$B$21>1,"Too small",IF($D38/$B$21<$B$12,"Looks < half",IF($E38/$B$21>$B$13,"Tight – test","OK"))) -> OK | K38: =IF($E38/$B$22>1,"Too small",IF($D38/$B$22<$B$12,"Looks < half",IF($E38/$B$22>$B$13,"Tight – test","OK"))) -> OK
A40: Takeaways
A41: • Balance (30ct) in a 4 oz jar: the pile is ~41% of the jar, just under half. That's the same as today's 120cc bottle. The owner chose to keep it. Confirm with a 30-capsule pour test.
A42: No North American stock line has a 2.5–3 oz amber straight-sided jar (they jump from 2 oz to 4 oz), so there is no easy smaller jar.
A43: • 60ct: must be a 6 oz / 177–190 ml jar. An 8–9 oz jar looks less than half full if production lands on size 0. Avoid anything over ~190 ml (e.g. a Chinese 7 oz / 200 ml).
A44: • 90ct: a 9 oz (266 ml) jar works for size 0 or 00. A 250 ml jar works but is close to the limit for size 00. An 8 oz is tight for size 00.
A45: • FINAL PLAN uses an 8 oz (237 ml; ~270 ml brim-full) for the 90ct. It looks ~61% full if size 0 and still fits size 00 (snug at nominal, ~81% of brim-full). A 9 oz is borderline (~54%) if size 0.
A46: • So every option now needs three jar sizes: ~4 oz, ~6 oz and ~9 oz. Lines with only 4 + 8/9 oz (Uline, Richards, Liquid Bottles) can't do the 60ct.
A47: • These are estimates. Before ordering at volume, fill one sample jar of each size with real capsules.

Sheet Regular Finish – Top 3
A1: Amber Straight-Sided Jars – REGULAR (glossy) finish: Top 3 single-source options (all three SKUs from one supplier)
A2: Ranked by landed cost (CAD/unit). Each option must fit all 3 SKUs AND pass the half-full rule, so the 60ct needs a ~6 oz jar. The 'if US-made' columns add the reported 50% surtax. Prices are from indexed supplier pages, Oct 2026 – verify by quote.
A4: #1 BURCH BOTTLE & PACKAGING (New York, US) – 4 oz / 6 oz / 9 oz, black PP caps
A5: Lowest North American cost. One of only three distributors with a true 6 oz amber (the others are Fillmore and Containers & Packaging Supply). Volume tiers published; deep stock. Country of origin unknown; if the jars are US-made the 50% surtax applies.
A6: SKU | B6: Jar used | C6: Supplier item # | D6: Neck | E6: Qty | F6: Currency | G6: Jar case price | H6: Case pack | I6: Jar unit price | J6: Cap / liner | K6: Cap unit price | L6: FX to CAD | M6: Jar + cap (CAD/unit) | N6: Decoration (CAD/unit) | O6: Freight & one-time costs (CAD/unit) | P6: LANDED (CAD/unit) | Q6: Extended (CAD) | R6: 50% surtax IF jar is US-made (jar value, CAD/unit) | S6: LANDED if US-made (CAD/unit) | T6: Extended if US-made (CAD) | U6: vs benchmark (CAD/unit) | V6: Price status
A7: Balance – 30x size 0 | B7: 4 oz | C7: 1SSA042GHG | D7: 58-400 | E7: =Inputs!$B$5 -> 2000 | F7: USD | G7: 11.45 | H7: 24 | I7: =G7/H7 -> 0.47708333 | J7: 2BP0581PX black PP ribbed (PE foam per spec) | K7: 0.14 | L7: =IF(F7="USD",Inputs!$B$10,1) -> 1.424 | M7: =(I7+K7)*L7*(1+Inputs!$B$33) -> 0.87872667 | N7: 0 | O7: =$O$11/SUM($E$7:$E$9) -> 0.36686667 | P7: =M7+N7+O7 -> 1.2455933 | Q7: =P7*E7 -> 2491.1867 | R7: =I7*L7*Inputs!$B$34 -> 0.33968333 | S7: =P7+R7 -> 1.5852767 | T7: =S7*E7 -> 3170.5533 | U7: =Inputs!$B$15-P7 -> 2.1944067 | V7: Live web price, Oct 9, 2026 – confirm by quote
A8: New A – 60ct (0 or 00) | B8: 6 oz | C8: 1SSA062GHG | D8: 63-400 | E8: =Inputs!$B$6 -> 500 | F8: USD | G8: 8.13 | H8: 12 | I8: =G8/H8 -> 0.6775 | J8: 2BP0632PX black PP | K8: 0.13 | L8: =IF(F8="USD",Inputs!$B$10,1) -> 1.424 | M8: =(I8+K8)*L8*(1+Inputs!$B$33) -> 1.14988 | N8: 0 | O8: =$O$11/SUM($E$7:$E$9) -> 0.36686667 | P8: =M8+N8+O8 -> 1.5167467 | Q8: =P8*E8 -> 758.37333 | R8: =I8*L8*Inputs!$B$34 -> 0.48238 | S8: =P8+R8 -> 1.9991267 | T8: =S8*E8 -> 999.56333 | U8: =Inputs!$B$15-P8 -> 1.9232533 | V8: Live web price, Oct 9, 2026 – confirm by quote
A9: New B – 90ct (0 or 00) | B9: 9 oz | C9: 1SSA092SGC | D9: 70-400 | E9: =Inputs!$B$7 -> 500 | F9: USD | G9: 5.29 | H9: 12 | I9: =G9/H9 -> 0.44083333 | J9: 2BP0701PX black PP (PS22 tamper-evident: 2BP0706MR $0.30) | K9: 0.17 | L9: =IF(F9="USD",Inputs!$B$10,1) -> 1.424 | M9: =(I9+K9)*L9*(1+Inputs!$B$33) -> 0.86982667 | N9: 0 | O9: =$O$11/SUM($E$7:$E$9) -> 0.36686667 | P9: =M9+N9+O9 -> 1.2366933 | Q9: =P9*E9 -> 618.34667 | R9: =I9*L9*Inputs!$B$34 -> 0.31387333 | S9: =P9+R9 -> 1.5505667 | T9: =S9*E9 -> 775.28333 | U9: =Inputs!$B$15-P9 -> 2.2033067 | V9: Live web price, Oct 9, 2026 – confirm by quote. 9 oz looks ~54% full if size 0.
A10: TOTAL / weighted average | E10: =SUM(E7:E9) -> 3000 | P10: =Q10/E10 -> 1.2893022 | Q10: =SUM(Q7:Q9) -> 3867.9067 | S10: =T10/E10 -> 1.6484667 | T10: =SUM(T7:T9) -> 4945.4 | U10: =Inputs!$B$15-P10 -> 2.1506978
A11: One-time / shared costs (freight, brokerage, setup, QC) allocated across all units: | O11: =Inputs!$B$18*Inputs!$B$10+Inputs!$B$19 -> 1100.6 | P11: Calc: US LTL freight × FX + brokerage (Inputs)
A13: #2 FILLMORE CONTAINER (Pennsylvania, US) – 4 oz / 6 oz / 9 oz, black PP caps
A14: Same 4/6/9 oz structure as Burch, ~10% higher. FAQ confirms ground and freight shipping to Canada (buyer pays duties/fees). Country of origin unknown.
A15: SKU | B15: Jar used | C15: Supplier item # | D15: Neck | E15: Qty | F15: Currency | G15: Jar case price | H15: Case pack | I15: Jar unit price | J15: Cap / liner | K15: Cap unit price | L15: FX to CAD | M15: Jar + cap (CAD/unit) | N15: Decoration (CAD/unit) | O15: Freight & one-time costs (CAD/unit) | P15: LANDED (CAD/unit) | Q15: Extended (CAD) | R15: 50% surtax IF jar is US-made (jar value, CAD/unit) | S15: LANDED if US-made (CAD/unit) | T15: Extended if US-made (CAD) | U15: vs benchmark (CAD/unit) | V15: Price status
A16: Balance – 30x size 0 | B16: 4 oz | C16: R04-30C (case 24) | D16: 58-400 | E16: =Inputs!$B$5 -> 2000 | F16: USD | G16: 12.95 | H16: 24 | I16: =G16/H16 -> 0.53958333 | J16: RC-058 PBMR black PP, F217 liner | K16: 0.125 | L16: =IF(F16="USD",Inputs!$B$10,1) -> 1.424 | M16: =(I16+K16)*L16*(1+Inputs!$B$33) -> 0.94636667 | N16: 0 | O16: =$O$20/SUM($E$16:$E$18) -> 0.36686667 | P16: =M16+N16+O16 -> 1.3132333 | Q16: =P16*E16 -> 2626.4667 | R16: =I16*L16*Inputs!$B$34 -> 0.38418333 | S16: =P16+R16 -> 1.6974167 | T16: =S16*E16 -> 3394.8333 | U16: =Inputs!$B$15-P16 -> 2.1267667 | V16: Live web price, Oct 9, 2026 – confirm by quote
A17: New A – 60ct (0 or 00) | B17: 6 oz | C17: B06-30C (case 12) | D17: 63-400 | E17: =Inputs!$B$6 -> 500 | F17: USD | G17: 7.99 | H17: 12 | I17: =G17/H17 -> 0.66583333 | J17: RC-063 PBMR black PP, F217 liner (Made in USA) | K17: 0.2 | L17: =IF(F17="USD",Inputs!$B$10,1) -> 1.424 | M17: =(I17+K17)*L17*(1+Inputs!$B$33) -> 1.2329467 | N17: 0 | O17: =$O$20/SUM($E$16:$E$18) -> 0.36686667 | P17: =M17+N17+O17 -> 1.5998133 | Q17: =P17*E17 -> 799.90667 | R17: =I17*L17*Inputs!$B$34 -> 0.47407333 | S17: =P17+R17 -> 2.0738867 | T17: =S17*E17 -> 1036.9433 | U17: =Inputs!$B$15-P17 -> 1.8401867 | V17: Live web price, Oct 9, 2026 – confirm by quote
A18: New B – 90ct (0 or 00) | B18: 9 oz | C18: B09-30C (case 12) | D18: 70-400 | E18: =Inputs!$B$7 -> 500 | F18: USD | G18: 6.35 | H18: 12 | I18: =G18/H18 -> 0.52916667 | J18: RC-070/400 PBS black smooth, F217 liner | K18: 0.22 | L18: =IF(F18="USD",Inputs!$B$10,1) -> 1.424 | M18: =(I18+K18)*L18*(1+Inputs!$B$33) -> 1.0668133 | N18: 0 | O18: =$O$20/SUM($E$16:$E$18) -> 0.36686667 | P18: =M18+N18+O18 -> 1.43368 | Q18: =P18*E18 -> 716.84 | R18: =I18*L18*Inputs!$B$34 -> 0.37676667 | S18: =P18+R18 -> 1.8104467 | T18: =S18*E18 -> 905.22333 | U18: =Inputs!$B$15-P18 -> 2.00632 | V18: Live web price, Oct 9, 2026 – confirm by quote
A19: TOTAL / weighted average | E19: =SUM(E16:E18) -> 3000 | P19: =Q19/E19 -> 1.3810711 | Q19: =SUM(Q16:Q18) -> 4143.2133 | S19: =T19/E19 -> 1.779 | T19: =SUM(T16:T18) -> 5337 | U19: =Inputs!$B$15-P19 -> 2.0589289
A20: One-time / shared costs (freight, brokerage, setup, QC) allocated across all units: | O20: =Inputs!$B$18*Inputs!$B$10+Inputs!$B$19 -> 1100.6 | P20: Calc: US LTL freight × FX + brokerage (Inputs)
A22: #3 CHINA DIRECT FACTORY – 120 ml / 180–190 ml / 250–270 ml, black PP caps + glass-rated liner
A23: Cheapest even with LCL freight and QC costs, and no surtax (MFN duty Free). BUT 10–13 weeks including sampling, so it can't serve the urgent launch. No single factory listed all three necks; make 58/63/70-400 a hard RFQ requirement.
A24: SKU | B24: Jar used | C24: Supplier item # | D24: Neck | E24: Qty | F24: Currency | G24: Jar case price | H24: Case pack | I24: Jar unit price | J24: Cap / liner | K24: Cap unit price | L24: FX to CAD | M24: Jar + cap (CAD/unit) | N24: Decoration (CAD/unit) | O24: Freight & one-time costs (CAD/unit) | P24: LANDED (CAD/unit) | Q24: Extended (CAD) | R24: 50% surtax IF jar is US-made (jar value, CAD/unit) | S24: LANDED if US-made (CAD/unit) | T24: Extended if US-made (CAD) | U24: vs benchmark (CAD/unit) | V24: Price status
A25: Balance – 30x size 0 | B25: 120 ml | C25: amber SS jar – Xuzhou Das / Qingdao Giant / Sheenland (RFQ) | D25: 58-400 (specify) | E25: =Inputs!$B$5 -> 2000 | F25: USD | G25: n/a | I25: 0.42 | J25: Black PP cap + glass-rated induction or PS22 liner | K25: 0.07 | L25: =IF(F25="USD",Inputs!$B$10,1) -> 1.424 | M25: =(I25+K25)*L25*(1+Inputs!$B$33) -> 0.69776 | N25: 0 | O25: =$O$29/SUM($E$25:$E$27) -> 0.61666667 | P25: =M25+N25+O25 -> 1.3144267 | Q25: =P25*E25 -> 2628.8533 | R25: 0 | S25: =P25+R25 -> 1.3144267 | T25: =S25*E25 -> 2628.8533 | U25: =Inputs!$B$15-P25 -> 2.1255733 | V25: ESTIMATE from Alibaba / Made-in-China listings – RFQ required
A26: New A – 60ct (0 or 00) | B26: 180–190 ml | C26: amber SS jar – Sincereal / Qingdao Xinte / Qingdao Giant (RFQ) | D26: 63-400 (specify) | E26: =Inputs!$B$6 -> 500 | F26: USD | G26: n/a | I26: 0.48 | J26: Black PP cap + glass-rated liner | K26: 0.07 | L26: =IF(F26="USD",Inputs!$B$10,1) -> 1.424 | M26: =(I26+K26)*L26*(1+Inputs!$B$33) -> 0.7832 | N26: 0 | O26: =$O$29/SUM($E$25:$E$27) -> 0.61666667 | P26: =M26+N26+O26 -> 1.3998667 | Q26: =P26*E26 -> 699.93333 | R26: 0 | S26: =P26+R26 -> 1.3998667 | T26: =S26*E26 -> 699.93333 | U26: =Inputs!$B$15-P26 -> 2.0401333 | V26: ESTIMATE from Alibaba / Made-in-China listings – RFQ required. Confirm 180–190 ml at 500 units.
A27: New B – 90ct (0 or 00) | B27: 250 ml | C27: amber SS jar – Xuzhou Das 8 oz / Xuzhou Huiju 70-400 | D27: 70-400 | E27: =Inputs!$B$7 -> 500 | F27: USD | G27: n/a | I27: 0.42 | J27: Black PP cap + glass-rated liner | K27: 0.07 | L27: =IF(F27="USD",Inputs!$B$10,1) -> 1.424 | M27: =(I27+K27)*L27*(1+Inputs!$B$33) -> 0.69776 | N27: 0 | O27: =$O$29/SUM($E$25:$E$27) -> 0.61666667 | P27: =M27+N27+O27 -> 1.3144267 | Q27: =P27*E27 -> 657.21333 | R27: 0 | S27: =P27+R27 -> 1.3144267 | T27: =S27*E27 -> 657.21333 | U27: =Inputs!$B$15-P27 -> 2.1255733 | V27: ESTIMATE from Alibaba / Made-in-China listings – RFQ required. For future 90ct reorders.
A28: TOTAL / weighted average | E28: =SUM(E25:E27) -> 3000 | P28: =Q28/E28 -> 1.3286667 | Q28: =SUM(Q25:Q27) -> 3986 | S28: =T28/E28 -> 1.3286667 | T28: =SUM(T25:T27) -> 3986 | U28: =Inputs!$B$15-P28 -> 2.1113333
A29: One-time / shared costs (freight, brokerage, setup, QC) allocated across all units: | O29: =Inputs!$B$21+Inputs!$B$30 -> 1850 | P29: Calc: China LCL door-to-door + samples/QC (Inputs)
A31: REFERENCE (fails the half-full rule for the 60ct): RICHARDS PACKAGING (Canada) – 4 oz / 9 oz
A32: Canadian stock, CAD pricing, no border. Both jars are made in China (verified), so no surtax. No 6 oz, so it can't do the 60ct. Its 9 oz IS a strong option for the 90ct in a split order (see Split Plan sheet). Cap price is a placeholder (quote required).
A33: SKU | B33: Jar used | C33: Supplier item # | D33: Neck | E33: Qty | F33: Currency | G33: Jar case price | H33: Case pack | I33: Jar unit price | J33: Cap / liner | K33: Cap unit price | L33: FX to CAD | M33: Jar + cap (CAD/unit) | N33: Decoration (CAD/unit) | O33: Freight & one-time costs (CAD/unit) | P33: LANDED (CAD/unit) | Q33: Extended (CAD) | R33: 50% surtax IF jar is US-made (jar value, CAD/unit) | S33: LANDED if US-made (CAD/unit) | T33: Extended if US-made (CAD) | U33: vs benchmark (CAD/unit) | V33: Price status
A34: Balance – 30x size 0 | B34: 4 oz | C34: RP-1159A / 40210181 | D34: 58-400 | E34: =Inputs!$B$5 -> 2000 | F34: CAD | G34: n/a | H34: 24 | I34: 0.96 | J34: 32110846 58-400 black PP smooth, foam liner | K34: 0.5 | L34: =IF(F34="USD",Inputs!$B$10,1) -> 1 | M34: =(I34+K34)*L34*(1+Inputs!$B$33) -> 1.46 | N34: 0 | O34: =$O$38/SUM($E$34:$E$36) -> 0.1 | P34: =M34+N34+O34 -> 1.56 | Q34: =P34*E34 -> 3120 | R34: 0 | S34: =P34+R34 -> 1.56 | T34: =S34*E34 -> 3120 | U34: =Inputs!$B$15-P34 -> 1.88 | V34: Live list price; origin China (verified). Member price may be lower.
A35: New A – 60ct ✗ (9 oz looks < half) | B35: 9 oz | C35: RP-1001A / 40220146 | D35: 70-400 | E35: =Inputs!$B$6 -> 500 | F35: CAD | G35: n/a | H35: 12 | I35: 0.99 | J35: 70-400 black PP | K35: 0.25 | L35: =IF(F35="USD",Inputs!$B$10,1) -> 1 | M35: =(I35+K35)*L35*(1+Inputs!$B$33) -> 1.24 | N35: 0 | O35: =$O$38/SUM($E$34:$E$36) -> 0.1 | P35: =M35+N35+O35 -> 1.34 | Q35: =P35*E35 -> 670 | R35: 0 | S35: =P35+R35 -> 1.34 | T35: =S35*E35 -> 670 | U35: =Inputs!$B$15-P35 -> 2.1 | V35: FAILS half-full rule for 60ct
A36: New B – 90ct (0 or 00) | B36: 9 oz | C36: RP-1001A / 40220146 | D36: 70-400 | E36: =Inputs!$B$7 -> 500 | F36: CAD | G36: n/a | H36: 12 | I36: 0.99 | J36: 32110979 70 mm black PP deep-skirt, PE foam | K36: 0.25 | L36: =IF(F36="USD",Inputs!$B$10,1) -> 1 | M36: =(I36+K36)*L36*(1+Inputs!$B$33) -> 1.24 | N36: 0 | O36: =$O$38/SUM($E$34:$E$36) -> 0.1 | P36: =M36+N36+O36 -> 1.34 | Q36: =P36*E36 -> 670 | R36: 0 | S36: =P36+R36 -> 1.34 | T36: =S36*E36 -> 670 | U36: =Inputs!$B$15-P36 -> 2.1 | V36: Live list price. 9 oz looks ~54% full if size 0.
A37: TOTAL / weighted average | E37: =SUM(E34:E36) -> 3000 | P37: =Q37/E37 -> 1.4866667 | Q37: =SUM(Q34:Q36) -> 4460 | S37: =T37/E37 -> 1.4866667 | T37: =SUM(T34:T36) -> 4460 | U37: =Inputs!$B$15-P37 -> 1.9533333
A38: One-time / shared costs (freight, brokerage, setup, QC) allocated across all units: | O38: =Inputs!$B$20 -> 300 | P38: Calc: Domestic Canada freight (Inputs)
A40: REFERENCE (fails the half-full rule for the 60ct): ULINE CANADA – the jar your designer linked – 4 oz / 8 oz
A41: Fast and Canadian, but about 2x the cost. No 6 oz. Uline says its phenolic pulp/vinyl cap is not airtight and can't be induction sealed. Fine for samples.
A42: SKU | B42: Jar used | C42: Supplier item # | D42: Neck | E42: Qty | F42: Currency | G42: Jar case price | H42: Case pack | I42: Jar unit price | J42: Cap / liner | K42: Cap unit price | L42: FX to CAD | M42: Jar + cap (CAD/unit) | N42: Decoration (CAD/unit) | O42: Freight & one-time costs (CAD/unit) | P42: LANDED (CAD/unit) | Q42: Extended (CAD) | R42: 50% surtax IF jar is US-made (jar value, CAD/unit) | S42: LANDED if US-made (CAD/unit) | T42: Extended if US-made (CAD) | U42: vs benchmark (CAD/unit) | V42: Price status
A43: Balance – 30x size 0 | B43: 4 oz | C43: S-24532 | D43: 58-400 | E43: =Inputs!$B$5 -> 2000 | F43: CAD | G43: n/a | H43: 24 | I43: 1.67 | J43: Black phenolic, pulp/vinyl liner (included) | K43: 0 | L43: =IF(F43="USD",Inputs!$B$10,1) -> 1 | M43: =(I43+K43)*L43*(1+Inputs!$B$33) -> 1.67 | N43: 0 | O43: =$O$47/SUM($E$43:$E$45) -> 0.1 | P43: =M43+N43+O43 -> 1.77 | Q43: =P43*E43 -> 3540 | R43: 0 | S43: =P43+R43 -> 1.77 | T43: =S43*E43 -> 3540 | U43: =Inputs!$B$15-P43 -> 1.67 | V43: Indexed web price (uline.ca)
A44: New A – 60ct ✗ (8 oz looks < half if size 0) | B44: 8 oz | C44: S-24533 | D44: 70-400 | E44: =Inputs!$B$6 -> 500 | F44: CAD | G44: n/a | H44: 24 | I44: 2.35 | J44: Black phenolic, pulp/vinyl liner (included) | K44: 0 | L44: =IF(F44="USD",Inputs!$B$10,1) -> 1 | M44: =(I44+K44)*L44*(1+Inputs!$B$33) -> 2.35 | N44: 0 | O44: =$O$47/SUM($E$43:$E$45) -> 0.1 | P44: =M44+N44+O44 -> 2.45 | Q44: =P44*E44 -> 1225 | R44: 0 | S44: =P44+R44 -> 2.45 | T44: =S44*E44 -> 1225 | U44: =Inputs!$B$15-P44 -> 0.99 | V44: FAILS half-full rule for 60ct at size 0
A45: New B – 90ct (0 or 00) | B45: 8 oz | C45: S-24533 | D45: 70-400 | E45: =Inputs!$B$7 -> 500 | F45: CAD | G45: n/a | H45: 24 | I45: 2.35 | J45: Black phenolic, pulp/vinyl liner (included) | K45: 0 | L45: =IF(F45="USD",Inputs!$B$10,1) -> 1 | M45: =(I45+K45)*L45*(1+Inputs!$B$33) -> 2.35 | N45: 0 | O45: =$O$47/SUM($E$43:$E$45) -> 0.1 | P45: =M45+N45+O45 -> 2.45 | Q45: =P45*E45 -> 1225 | R45: 0 | S45: =P45+R45 -> 2.45 | T45: =S45*E45 -> 1225 | U45: =Inputs!$B$15-P45 -> 0.99 | V45: Indexed web price. 90x00 tight in 8 oz – test.
A46: TOTAL / weighted average | E46: =SUM(E43:E45) -> 3000 | P46: =Q46/E46 -> 1.9966667 | Q46: =SUM(Q43:Q45) -> 5990 | S46: =T46/E46 -> 1.9966667 | T46: =SUM(T43:T45) -> 5990 | U46: =Inputs!$B$15-P46 -> 1.4433333
A47: One-time / shared costs (freight, brokerage, setup, QC) allocated across all units: | O47: =Inputs!$B$20 -> 300 | P47: Calc: Domestic Canada freight (Inputs)

Sheet Frosted Finish – Top 3
A1: Amber Straight-Sided Jars – MATTE / FROSTED finish: Top 3 single-source options (all three SKUs from one supplier)
A2: No North American distributor stocks frosted amber straight-sided jars in 4 + 6 + 9 oz. The designer's Bottle Depot jar is frosted only up to 4 oz. So frosted means China direct, or plain amber jars frosted by a decorator.
A4: #1 CHINA DIRECT FACTORY – frosted amber 120 ml / 180–190 ml / 250–270 ml
A5: Lowest cost by far, with a true acid-etched/sandblasted frost (more durable than spray). No surtax. 10–13 weeks including sampling, so it can't serve the urgent launch. Xuzhou Das lists frosted amber 2/4/8 oz at MOQ 2,000; a 180–190 ml frosted size needs RFQ confirmation.
A6: SKU | B6: Jar used | C6: Supplier item # | D6: Neck | E6: Qty | F6: Currency | G6: Jar case price | H6: Case pack | I6: Jar unit price | J6: Cap / liner | K6: Cap unit price | L6: FX to CAD | M6: Jar + cap (CAD/unit) | N6: Decoration (CAD/unit) | O6: Freight & one-time costs (CAD/unit) | P6: LANDED (CAD/unit) | Q6: Extended (CAD) | R6: 50% surtax IF jar is US-made (jar value, CAD/unit) | S6: LANDED if US-made (CAD/unit) | T6: Extended if US-made (CAD) | U6: vs benchmark (CAD/unit) | V6: Price status
A7: Balance – 30x size 0 | B7: 120 ml | C7: frosted (acid-etch/sandblast) amber SS jar – Xuzhou Das / Qingdao Giant / Sheenland (RFQ) | D7: 58-400 (specify) | E7: =Inputs!$B$5 -> 2000 | F7: USD | G7: n/a | I7: 0.46 | J7: Black PP cap + glass-rated induction or PS22 liner | K7: 0.07 | L7: =IF(F7="USD",Inputs!$B$10,1) -> 1.424 | M7: =(I7+K7)*L7*(1+Inputs!$B$33) -> 0.75472 | N7: 0 | O7: =$O$11/SUM($E$7:$E$9) -> 0.61666667 | P7: =M7+N7+O7 -> 1.3713867 | Q7: =P7*E7 -> 2742.7733 | R7: 0 | S7: =P7+R7 -> 1.3713867 | T7: =S7*E7 -> 2742.7733 | U7: =Inputs!$B$15-P7 -> 2.0686133 | V7: ESTIMATE from Alibaba / Made-in-China listings – RFQ required
A8: New A – 60ct (0 or 00) | B8: 180–190 ml | C8: frosted (acid-etch/sandblast) amber SS jar – Sincereal / Qingdao Xinte / Qingdao Giant (RFQ) | D8: 63-400 (specify) | E8: =Inputs!$B$6 -> 500 | F8: USD | G8: n/a | I8: 0.6 | J8: Black PP cap + glass-rated liner | K8: 0.07 | L8: =IF(F8="USD",Inputs!$B$10,1) -> 1.424 | M8: =(I8+K8)*L8*(1+Inputs!$B$33) -> 0.95408 | N8: 0 | O8: =$O$11/SUM($E$7:$E$9) -> 0.61666667 | P8: =M8+N8+O8 -> 1.5707467 | Q8: =P8*E8 -> 785.37333 | R8: 0 | S8: =P8+R8 -> 1.5707467 | T8: =S8*E8 -> 785.37333 | U8: =Inputs!$B$15-P8 -> 1.8692533 | V8: ESTIMATE from Alibaba / Made-in-China listings – RFQ required. Confirm 180–190 ml at 500 units.
A9: New B – 90ct (0 or 00) | B9: 250 ml | C9: frosted (acid-etch/sandblast) amber SS jar – Xuzhou Das 8 oz / Xuzhou Huiju 70-400 | D9: 70-400 | E9: =Inputs!$B$7 -> 500 | F9: USD | G9: n/a | I9: 0.55 | J9: Black PP cap + glass-rated liner | K9: 0.07 | L9: =IF(F9="USD",Inputs!$B$10,1) -> 1.424 | M9: =(I9+K9)*L9*(1+Inputs!$B$33) -> 0.88288 | N9: 0 | O9: =$O$11/SUM($E$7:$E$9) -> 0.61666667 | P9: =M9+N9+O9 -> 1.4995467 | Q9: =P9*E9 -> 749.77333 | R9: 0 | S9: =P9+R9 -> 1.4995467 | T9: =S9*E9 -> 749.77333 | U9: =Inputs!$B$15-P9 -> 1.9404533 | V9: ESTIMATE from Alibaba / Made-in-China listings – RFQ required. For future 90ct reorders.
A10: TOTAL / weighted average | E10: =SUM(E7:E9) -> 3000 | P10: =Q10/E10 -> 1.4259733 | Q10: =SUM(Q7:Q9) -> 4277.92 | S10: =T10/E10 -> 1.4259733 | T10: =SUM(T7:T9) -> 4277.92 | U10: =Inputs!$B$15-P10 -> 2.0140267
A11: One-time / shared costs (freight, brokerage, setup, QC) allocated across all units: | O11: =Inputs!$B$21+Inputs!$B$30 -> 1850 | P11: Calc: China LCL door-to-door + samples/QC (Inputs)
A13: #2 BURCH plain amber (4/6/9 oz) + SPRAY-FROSTED by a Canadian decorator (e.g. Stanpac Ink, Ontario)
A14: Best North American route: real 6 oz, stock jars, ~3–6 weeks. Jar and cap prices as Regular #1. Frosting is a CAD estimate (quote required). Spray frost is a lacquer, so test for scuffing.
A15: SKU | B15: Jar used | C15: Supplier item # | D15: Neck | E15: Qty | F15: Currency | G15: Jar case price | H15: Case pack | I15: Jar unit price | J15: Cap / liner | K15: Cap unit price | L15: FX to CAD | M15: Jar + cap (CAD/unit) | N15: Decoration (CAD/unit) | O15: Freight & one-time costs (CAD/unit) | P15: LANDED (CAD/unit) | Q15: Extended (CAD) | R15: 50% surtax IF jar is US-made (jar value, CAD/unit) | S15: LANDED if US-made (CAD/unit) | T15: Extended if US-made (CAD) | U15: vs benchmark (CAD/unit) | V15: Price status
A16: Balance – 30x size 0 | B16: 4 oz | C16: 1SSA042GHG | D16: 58-400 | E16: =Inputs!$B$5 -> 2000 | F16: USD | G16: 11.45 | H16: 24 | I16: =G16/H16 -> 0.47708333 | J16: 2BP0581PX black PP ribbed (PE foam per spec) | K16: 0.14 | L16: =IF(F16="USD",Inputs!$B$10,1) -> 1.424 | M16: =(I16+K16)*L16*(1+Inputs!$B$33) -> 0.87872667 | N16: =Inputs!$B$37 -> 0.45 | O16: =$O$20/SUM($E$16:$E$18) -> 1.1168667 | P16: =M16+N16+O16 -> 2.4455933 | Q16: =P16*E16 -> 4891.1867 | R16: =I16*L16*Inputs!$B$34 -> 0.33968333 | S16: =P16+R16 -> 2.7852767 | T16: =S16*E16 -> 5570.5533 | U16: =Inputs!$B$15-P16 -> 0.99440667 | V16: Jar/cap: indexed web price. Frosting: ESTIMATE – quote required
A17: New A – 60ct (0 or 00) | B17: 6 oz | C17: 1SSA062GHG | D17: 63-400 | E17: =Inputs!$B$6 -> 500 | F17: USD | G17: 8.13 | H17: 12 | I17: =G17/H17 -> 0.6775 | J17: 2BP0632PX black PP | K17: 0.13 | L17: =IF(F17="USD",Inputs!$B$10,1) -> 1.424 | M17: =(I17+K17)*L17*(1+Inputs!$B$33) -> 1.14988 | N17: =Inputs!$B$37 -> 0.45 | O17: =$O$20/SUM($E$16:$E$18) -> 1.1168667 | P17: =M17+N17+O17 -> 2.7167467 | Q17: =P17*E17 -> 1358.3733 | R17: =I17*L17*Inputs!$B$34 -> 0.48238 | S17: =P17+R17 -> 3.1991267 | T17: =S17*E17 -> 1599.5633 | U17: =Inputs!$B$15-P17 -> 0.72325333 | V17: Jar/cap: indexed web price. Frosting: ESTIMATE – quote required
A18: New B – 90ct (0 or 00) | B18: 9 oz | C18: 1SSA092SGC | D18: 70-400 | E18: =Inputs!$B$7 -> 500 | F18: USD | G18: 5.29 | H18: 12 | I18: =G18/H18 -> 0.44083333 | J18: 2BP0701PX black PP (PS22 tamper-evident: 2BP0706MR $0.30) | K18: 0.17 | L18: =IF(F18="USD",Inputs!$B$10,1) -> 1.424 | M18: =(I18+K18)*L18*(1+Inputs!$B$33) -> 0.86982667 | N18: =Inputs!$B$37 -> 0.45 | O18: =$O$20/SUM($E$16:$E$18) -> 1.1168667 | P18: =M18+N18+O18 -> 2.4366933 | Q18: =P18*E18 -> 1218.3467 | R18: =I18*L18*Inputs!$B$34 -> 0.31387333 | S18: =P18+R18 -> 2.7505667 | T18: =S18*E18 -> 1375.2833 | U18: =Inputs!$B$15-P18 -> 1.0033067 | V18: Jar/cap: indexed web price. Frosting: ESTIMATE – quote required
A19: TOTAL / weighted average | E19: =SUM(E16:E18) -> 3000 | P19: =Q19/E19 -> 2.4893022 | Q19: =SUM(Q16:Q18) -> 7467.9067 | S19: =T19/E19 -> 2.8484667 | T19: =SUM(T16:T18) -> 8545.4 | U19: =Inputs!$B$15-P19 -> 0.95069778
A20: One-time / shared costs (freight, brokerage, setup, QC) allocated across all units: | O20: =Inputs!$B$18*Inputs!$B$10+Inputs!$B$19+Inputs!$B$38*Inputs!$B$9+Inputs!$B$39 -> 3350.6 | P20: Calc: US freight × FX + brokerage + frost setup × SKUs + decorator freight (Inputs)
A22: #3 FILLMORE plain amber (4/6/9 oz) + SPRAY-FROSTED by a Canadian decorator
A23: Same route as #2 using Fillmore jars. Slightly dearer, but Fillmore explicitly ships to Canada.
A24: SKU | B24: Jar used | C24: Supplier item # | D24: Neck | E24: Qty | F24: Currency | G24: Jar case price | H24: Case pack | I24: Jar unit price | J24: Cap / liner | K24: Cap unit price | L24: FX to CAD | M24: Jar + cap (CAD/unit) | N24: Decoration (CAD/unit) | O24: Freight & one-time costs (CAD/unit) | P24: LANDED (CAD/unit) | Q24: Extended (CAD) | R24: 50% surtax IF jar is US-made (jar value, CAD/unit) | S24: LANDED if US-made (CAD/unit) | T24: Extended if US-made (CAD) | U24: vs benchmark (CAD/unit) | V24: Price status
A25: Balance – 30x size 0 | B25: 4 oz | C25: R04-30C (case 24) | D25: 58-400 | E25: =Inputs!$B$5 -> 2000 | F25: USD | G25: 12.95 | H25: 24 | I25: =G25/H25 -> 0.53958333 | J25: RC-058 PBMR black PP, F217 liner | K25: 0.125 | L25: =IF(F25="USD",Inputs!$B$10,1) -> 1.424 | M25: =(I25+K25)*L25*(1+Inputs!$B$33) -> 0.94636667 | N25: =Inputs!$B$37 -> 0.45 | O25: =$O$29/SUM($E$25:$E$27) -> 1.1168667 | P25: =M25+N25+O25 -> 2.5132333 | Q25: =P25*E25 -> 5026.4667 | R25: =I25*L25*Inputs!$B$34 -> 0.38418333 | S25: =P25+R25 -> 2.8974167 | T25: =S25*E25 -> 5794.8333 | U25: =Inputs!$B$15-P25 -> 0.92676667 | V25: Jar/cap: indexed web price. Frosting: ESTIMATE – quote required
A26: New A – 60ct (0 or 00) | B26: 6 oz | C26: B06-30C (case 12) | D26: 63-400 | E26: =Inputs!$B$6 -> 500 | F26: USD | G26: 7.99 | H26: 12 | I26: =G26/H26 -> 0.66583333 | J26: RC-063 PBMR black PP, F217 liner (Made in USA) | K26: 0.2 | L26: =IF(F26="USD",Inputs!$B$10,1) -> 1.424 | M26: =(I26+K26)*L26*(1+Inputs!$B$33) -> 1.2329467 | N26: =Inputs!$B$37 -> 0.45 | O26: =$O$29/SUM($E$25:$E$27) -> 1.1168667 | P26: =M26+N26+O26 -> 2.7998133 | Q26: =P26*E26 -> 1399.9067 | R26: =I26*L26*Inputs!$B$34 -> 0.47407333 | S26: =P26+R26 -> 3.2738867 | T26: =S26*E26 -> 1636.9433 | U26: =Inputs!$B$15-P26 -> 0.64018667 | V26: Jar/cap: indexed web price. Frosting: ESTIMATE – quote required
A27: New B – 90ct (0 or 00) | B27: 9 oz | C27: B09-30C (case 12) | D27: 70-400 | E27: =Inputs!$B$7 -> 500 | F27: USD | G27: 6.35 | H27: 12 | I27: =G27/H27 -> 0.52916667 | J27: RC-070/400 PBS black smooth, F217 liner | K27: 0.22 | L27: =IF(F27="USD",Inputs!$B$10,1) -> 1.424 | M27: =(I27+K27)*L27*(1+Inputs!$B$33) -> 1.0668133 | N27: =Inputs!$B$37 -> 0.45 | O27: =$O$29/SUM($E$25:$E$27) -> 1.1168667 | P27: =M27+N27+O27 -> 2.63368 | Q27: =P27*E27 -> 1316.84 | R27: =I27*L27*Inputs!$B$34 -> 0.37676667 | S27: =P27+R27 -> 3.0104467 | T27: =S27*E27 -> 1505.2233 | U27: =Inputs!$B$15-P27 -> 0.80632 | V27: Jar/cap: indexed web price. Frosting: ESTIMATE – quote required
A28: TOTAL / weighted average | E28: =SUM(E25:E27) -> 3000 | P28: =Q28/E28 -> 2.5810711 | Q28: =SUM(Q25:Q27) -> 7743.2133 | S28: =T28/E28 -> 2.979 | T28: =SUM(T25:T27) -> 8937 | U28: =Inputs!$B$15-P28 -> 0.85892889
A29: One-time / shared costs (freight, brokerage, setup, QC) allocated across all units: | O29: =Inputs!$B$18*Inputs!$B$10+Inputs!$B$19+Inputs!$B$38*Inputs!$B$9+Inputs!$B$39 -> 3350.6 | P29: Calc: US freight × FX + brokerage + frost setup × SKUs + decorator freight (Inputs)
A31: REFERENCE (fails): LIQUID BOTTLES (Florida, US) – 9 oz frosted amber only, OUT OF STOCK
A32: Live check: GJ402-F is PLAIN amber, not frosted (their only frosted 4 oz is frosted CLEAR). The 9 oz frosted amber (now GJ908-H2, $1.57) is out of stock. No frosted 6 or 8 oz. No North American seller has frosted amber 6 or 8 oz in small quantities.
A33: SKU | B33: Jar used | C33: Supplier item # | D33: Neck | E33: Qty | F33: Currency | G33: Jar case price | H33: Case pack | I33: Jar unit price | J33: Cap / liner | K33: Cap unit price | L33: FX to CAD | M33: Jar + cap (CAD/unit) | N33: Decoration (CAD/unit) | O33: Freight & one-time costs (CAD/unit) | P33: LANDED (CAD/unit) | Q33: Extended (CAD) | R33: 50% surtax IF jar is US-made (jar value, CAD/unit) | S33: LANDED if US-made (CAD/unit) | T33: Extended if US-made (CAD) | U33: vs benchmark (CAD/unit) | V33: Price status
A34: Balance – 30x size 0 | B34: 4 oz | C34: GJ402-F (PLAIN amber – not frosted) | D34: 58-400 | E34: =Inputs!$B$5 -> 2000 | F34: USD | G34: n/a | H34: 90 | I34: 0.75 | J34: 58-400 black PP, F217 liner | K34: 0.15 | L34: =IF(F34="USD",Inputs!$B$10,1) -> 1.424 | M34: =(I34+K34)*L34*(1+Inputs!$B$33) -> 1.2816 | N34: 0 | O34: =$O$38/SUM($E$34:$E$36) -> 0.36686667 | P34: =M34+N34+O34 -> 1.6484667 | Q34: =P34*E34 -> 3296.9333 | R34: =I34*L34*Inputs!$B$34 -> 0.534 | S34: =P34+R34 -> 2.1824667 | T34: =S34*E34 -> 4364.9333 | U34: =Inputs!$B$15-P34 -> 1.7915333 | V34: PLAIN amber – not frosted
A35: New A – 60ct ✗ (9 oz looks < half) | B35: 9 oz | C35: GJ908-H2 (frosted amber) | D35: 70-400 | E35: =Inputs!$B$6 -> 500 | F35: USD | G35: n/a | H35: 72 | I35: 1.57 | J35: 70-400 black PP, F217 liner | K35: 0.15 | L35: =IF(F35="USD",Inputs!$B$10,1) -> 1.424 | M35: =(I35+K35)*L35*(1+Inputs!$B$33) -> 2.44928 | N35: 0 | O35: =$O$38/SUM($E$34:$E$36) -> 0.36686667 | P35: =M35+N35+O35 -> 2.8161467 | Q35: =P35*E35 -> 1408.0733 | R35: =I35*L35*Inputs!$B$34 -> 1.11784 | S35: =P35+R35 -> 3.9339867 | T35: =S35*E35 -> 1966.9933 | U35: =Inputs!$B$15-P35 -> 0.62385333 | V35: FAILS half-full rule for 60ct
A36: New B – 90ct (0 or 00) | B36: 9 oz | C36: GJ908-H2 (frosted amber) | D36: 70-400 | E36: =Inputs!$B$7 -> 500 | F36: USD | G36: n/a | H36: 72 | I36: 1.57 | J36: PKCS070KPS-C 70-400 black PS22 | K36: 0.31 | L36: =IF(F36="USD",Inputs!$B$10,1) -> 1.424 | M36: =(I36+K36)*L36*(1+Inputs!$B$33) -> 2.67712 | N36: 0 | O36: =$O$38/SUM($E$34:$E$36) -> 0.36686667 | P36: =M36+N36+O36 -> 3.0439867 | Q36: =P36*E36 -> 1521.9933 | R36: =I36*L36*Inputs!$B$34 -> 1.11784 | S36: =P36+R36 -> 4.1618267 | T36: =S36*E36 -> 2080.9133 | U36: =Inputs!$B$15-P36 -> 0.39601333 | V36: OUT OF STOCK
A37: TOTAL / weighted average | E37: =SUM(E34:E36) -> 3000 | P37: =Q37/E37 -> 2.0756667 | Q37: =SUM(Q34:Q36) -> 6227 | S37: =T37/E37 -> 2.80428 | T37: =SUM(T34:T36) -> 8412.84 | U37: =Inputs!$B$15-P37 -> 1.3643333
A38: One-time / shared costs (freight, brokerage, setup, QC) allocated across all units: | O38: =Inputs!$B$18*Inputs!$B$10+Inputs!$B$19 -> 1100.6 | P38: Calc: US LTL freight × FX + brokerage (Inputs)

Sheet Split Plan – Local vs China
A1: Split sourcing: buy one launch SKU locally now, the other two from China (~3 months)?
A2: Plan A = all three SKUs bought locally. Plan B1 = 60ct jars local + Balance & 90ct from China. Plan B2 = 90ct jars local + Balance & 60ct from China. Plan C = all from China (reference: too slow for the urgent launch). Each line links to the Top 3 sheets for prices and to Inputs for freight.
A4: SCENARIO COMPARISON (lowest total in each finish highlighted green)
A5: Plan | B5: Description | C5: Total (CAD) – jars NOT US-made | D5: vs Plan A | E5: Total (CAD) – IF US jars are US-made (50% surtax) | F5: vs Plan A (surtax) | G5: Avg CAD/unit (no surtax) | H5: Meets launch timing?
A6: R-A | B6: Regular – all local (Burch; 90ct jar size guessed now) | C6: =N31 -> 3867.9067 | D6: =C6-N31 -> 0 | E6: =O31 -> 4945.4 | F6: =E6-O31 -> 0 | G6: =J31 -> 1.2893022 | H6: Yes
A7: R-B1 | B7: Regular – FLEX: 6 oz local; 90ct is size 00 → 60ct launches | C7: =N38 -> 4693.94 | D7: =C7-N31 -> 826.03333 | E7: =O38 -> 4935.13 | F7: =E7-O31 -> -10.27 | G7: =J38 -> 1.5646467 | H7: Yes
A8: R-FX0 | B8: Regular – FLEX: 6 oz local; 90ct is size 0 → 90ct launches | C8: =N45 -> 4716.66 | D8: =C8-N31 -> 848.75333 | E8: =O45 -> 4957.85 | F8: =E8-O31 -> 12.45 | G8: =J45 -> 1.57222 | H8: Yes
A9: R-B2 | B9: Regular – 90ct local (Burch 9 oz), rest China | C9: =N52 -> 4576.6333 | D9: =C9-N31 -> 708.72667 | E9: =O52 -> 4733.57 | F9: =E9-O31 -> -211.83 | G9: =J52 -> 1.5255444 | H9: Yes
A10: R-B2c | B10: Regular – 90ct local (Richards, Canada), rest China | C10: =N59 -> 4217.12 | D10: =C10-N31 -> 349.21333 | E10: =O59 -> 4217.12 | F10: =E10-O31 -> -728.28 | G10: =J59 -> 1.4057067 | H10: Yes
A11: R-C | B11: Regular – all China (reference) | C11: =N66 -> 3986 | D11: =C11-N31 -> 118.09333 | E11: =O66 -> 3986 | F11: =E11-O31 -> -959.4 | G11: =J66 -> 1.3286667 | H11: No – ~3 months
A12: F-A | B12: Frosted – all local (Burch + spray frost) | C12: =N74 -> 7467.9067 | D12: =C12-N74 -> 0 | E12: =O74 -> 8545.4 | F12: =E12-O74 -> 0 | G12: =J74 -> 2.4893022 | H12: Yes
A13: F-B1 | B13: Frosted – FLEX: 6 oz local; 90ct is size 00 → 60ct launches | C13: =N81 -> 6075.42 | D13: =C13-N74 -> -1392.4867 | E13: =O81 -> 6316.61 | F13: =E13-O74 -> -2228.79 | G13: =J81 -> 2.02514 | H13: Yes
A14: F-FX0 | B14: Frosted – FLEX: 6 oz local; 90ct is size 0 → 90ct launches | C14: =N88 -> 6091.02 | D14: =C14-N74 -> -1376.8867 | E14: =O88 -> 6332.21 | F14: =E14-O74 -> -2213.19 | G14: =J88 -> 2.03034 | H14: Yes
A15: F-B2 | B15: Frosted – 90ct local (Burch 9 oz + spray frost), rest China | C15: =N95 -> 5950.9933 | D15: =C15-N74 -> -1516.9133 | E15: =O95 -> 6107.93 | F15: =E15-O74 -> -2437.47 | G15: =J95 -> 1.9836644 | H15: Yes
A16: F-B2s | B16: Frosted – 90ct local (Liquid Bottles stock), rest China | C16: =N102 -> 5679.64 | D16: =C16-N74 -> -1788.2667 | E16: =O102 -> 6238.56 | F16: =E16-O74 -> -2306.84 | G16: =J102 -> 1.8932133 | H16: Yes, if in stock
A17: F-C | B17: Frosted – all China (reference) | C17: =N109 -> 4277.92 | D17: =C17-N74 -> -3189.9867 | E17: =O109 -> 4277.92 | F17: =E17-O74 -> -4267.48 | G17: =J109 -> 1.4259733 | H17: No – ~3 months
A18: How to read this
A19: • FINAL PLAN is on the 'Final Recommendation' tab (90ct in an 8 oz bought locally; Balance + 60ct from China). The FLEX PLAN rows were an earlier option: buy 2,000 x 6 oz locally now. At production, pour-test the 90ct. If it fits the 6 oz (size 0) → launch the 90ct; if not (size 00) → launch the 60ct. The 6 oz is used either way because the 60ct always needs it. Then order Balance + the remaining SKU's jar from China. Bold rows = the two possible outcomes.
A20: • 'vs Plan A' is negative when the plan is cheaper than buying everything locally. Note Plan A has to guess the 90ct jar now. A 9 oz looks ~54% full if it ends up size 0, which is borderline.
A21: • China's fixed costs (LCL freight with a 1 m³ minimum, brokerage, samples, QC) are spread over few jars at these volumes. That cancels most of China's cheaper glass for REGULAR jars, but not for FROSTED, where local spray-frosting is expensive.
A22: • The surtax columns only matter if the US distributor's jars were made in the USA. Richards (Canada; China-made) and China-direct jars are not affected.
A23: • Look consistency: in a split, the first-launch SKU's jar comes from a different maker (and for frosted, sprayed vs etched frost). You can switch it to the China jar at its first reorder.
A25: REGULAR (glossy) amber – scenario detail
A26: R-A – All local: Burch 4/6/9 oz in one shipment
A27: SKU | B27: Source | C27: Jar | D27: Ships from | E27: Jar + cap price (native) | F27: FX | G27: Goods (CAD/unit) | H27: Frosting (CAD/unit) | I27: Freight & one-time (CAD/unit) | J27: LANDED (CAD/unit) | K27: 50% surtax if US-made (CAD/unit) | L27: LANDED if US-made | M27: Qty | N27: Extended (CAD) | O27: Extended if US-made (CAD)
A28: Balance – 30ct | B28: Burch (local) | C28: ='Regular Finish – Top 3'!B7 -> 4 oz | D28: US | E28: ='Regular Finish – Top 3'!I7+'Regular Finish – Top 3'!K7 -> 0.61708333 | F28: ='Regular Finish – Top 3'!L7 -> 1.424 | G28: =E28*F28*(1+Inputs!$B$33) -> 0.87872667 | H28: 0 | I28: =(Inputs!$B$18*Inputs!$B$10+Inputs!$B$19)/Inputs!$B$8 -> 0.36686667 | J28: =G28+H28+I28 -> 1.2455933 | K28: ='Regular Finish – Top 3'!I7*F28*Inputs!$B$34 -> 0.33968333 | L28: =J28+K28 -> 1.5852767 | M28: =Inputs!$B$5 -> 2000 | N28: =J28*M28 -> 2491.1867 | O28: =L28*M28 -> 3170.5533
A29: New A – 60ct | B29: Burch (local) | C29: ='Regular Finish – Top 3'!B8 -> 6 oz | D29: US | E29: ='Regular Finish – Top 3'!I8+'Regular Finish – Top 3'!K8 -> 0.8075 | F29: ='Regular Finish – Top 3'!L8 -> 1.424 | G29: =E29*F29*(1+Inputs!$B$33) -> 1.14988 | H29: 0 | I29: =(Inputs!$B$18*Inputs!$B$10+Inputs!$B$19)/Inputs!$B$8 -> 0.36686667 | J29: =G29+H29+I29 -> 1.5167467 | K29: ='Regular Finish – Top 3'!I8*F29*Inputs!$B$34 -> 0.48238 | L29: =J29+K29 -> 1.9991267 | M29: =Inputs!$B$6 -> 500 | N29: =J29*M29 -> 758.37333 | O29: =L29*M29 -> 999.56333
A30: New B – 90ct | B30: Burch (local) | C30: ='Regular Finish – Top 3'!B9 -> 9 oz | D30: US | E30: ='Regular Finish – Top 3'!I9+'Regular Finish – Top 3'!K9 -> 0.61083333 | F30: ='Regular Finish – Top 3'!L9 -> 1.424 | G30: =E30*F30*(1+Inputs!$B$33) -> 0.86982667 | H30: 0 | I30: =(Inputs!$B$18*Inputs!$B$10+Inputs!$B$19)/Inputs!$B$8 -> 0.36686667 | J30: =G30+H30+I30 -> 1.2366933 | K30: ='Regular Finish – Top 3'!I9*F30*Inputs!$B$34 -> 0.31387333 | L30: =J30+K30 -> 1.5505667 | M30: =Inputs!$B$7 -> 500 | N30: =J30*M30 -> 618.34667 | O30: =L30*M30 -> 775.28333
A31: TOTAL / average | J31: =N31/M31 -> 1.2893022 | L31: =O31/M31 -> 1.6484667 | M31: =SUM(M28:M30) -> 3000 | N31: =SUM(N28:N30) -> 3867.9067 | O31: =SUM(O28:O30) -> 4945.4
A33: R-B1 – FLEX PLAN, outcome 90ct = size 00: 6 oz bought locally goes to the 60ct (launches first) · Balance + 90ct (9 oz / 250–270 ml) from China
A34: SKU | B34: Source | C34: Jar | D34: Ships from | E34: Jar + cap price (native) | F34: FX | G34: Goods (CAD/unit) | H34: Frosting (CAD/unit) | I34: Freight & one-time (CAD/unit) | J34: LANDED (CAD/unit) | K34: 50% surtax if US-made (CAD/unit) | L34: LANDED if US-made | M34: Qty | N34: Extended (CAD) | O34: Extended if US-made (CAD)
A35: Balance – 30ct | B35: China direct | C35: ='Regular Finish – Top 3'!B25 -> 120 ml | D35: China | E35: ='Regular Finish – Top 3'!I25+'Regular Finish – Top 3'!K25 -> 0.49 | F35: ='Regular Finish – Top 3'!L25 -> 1.424 | G35: =E35*F35*(1+Inputs!$B$33) -> 0.69776 | H35: 0 | I35: =(Inputs!$B$27+Inputs!$B$30)/(Inputs!$B$5+Inputs!$B$7) -> 0.672 | J35: =G35+H35+I35 -> 1.36976 | K35: 0 | L35: =J35+K35 -> 1.36976 | M35: =Inputs!$B$5 -> 2000 | N35: =J35*M35 -> 2739.52 | O35: =L35*M35 -> 2739.52
A36: New A – 60ct | B36: Burch (local, 1 pallet) | C36: ='Regular Finish – Top 3'!B8 -> 6 oz | D36: US | E36: ='Regular Finish – Top 3'!I8+'Regular Finish – Top 3'!K8 -> 0.8075 | F36: ='Regular Finish – Top 3'!L8 -> 1.424 | G36: =E36*F36*(1+Inputs!$B$33) -> 1.14988 | H36: 0 | I36: =(Inputs!$B$24*Inputs!$B$10+Inputs!$B$25)/Inputs!$B$6 -> 1.3892 | J36: =G36+H36+I36 -> 2.53908 | K36: ='Regular Finish – Top 3'!I8*F36*Inputs!$B$34 -> 0.48238 | L36: =J36+K36 -> 3.02146 | M36: =Inputs!$B$6 -> 500 | N36: =J36*M36 -> 1269.54 | O36: =L36*M36 -> 1510.73
A37: New B – 90ct | B37: China direct | C37: ='Regular Finish – Top 3'!B27 -> 250 ml | D37: China | E37: ='Regular Finish – Top 3'!I27+'Regular Finish – Top 3'!K27 -> 0.49 | F37: ='Regular Finish – Top 3'!L27 -> 1.424 | G37: =E37*F37*(1+Inputs!$B$33) -> 0.69776 | H37: 0 | I37: =(Inputs!$B$27+Inputs!$B$30)/(Inputs!$B$5+Inputs!$B$7) -> 0.672 | J37: =G37+H37+I37 -> 1.36976 | K37: 0 | L37: =J37+K37 -> 1.36976 | M37: =Inputs!$B$7 -> 500 | N37: =J37*M37 -> 684.88 | O37: =L37*M37 -> 684.88
A38: TOTAL / average | J38: =N38/M38 -> 1.5646467 | L38: =O38/M38 -> 1.6450433 | M38: =SUM(M35:M37) -> 3000 | N38: =SUM(N35:N37) -> 4693.94 | O38: =SUM(O35:O37) -> 4935.13
A40: R-FX0 – FLEX PLAN, outcome 90ct = size 0: 6 oz bought locally goes to the 90ct (launches first) · Balance + 60ct (6 oz) from China
A41: SKU | B41: Source | C41: Jar | D41: Ships from | E41: Jar + cap price (native) | F41: FX | G41: Goods (CAD/unit) | H41: Frosting (CAD/unit) | I41: Freight & one-time (CAD/unit) | J41: LANDED (CAD/unit) | K41: 50% surtax if US-made (CAD/unit) | L41: LANDED if US-made | M41: Qty | N41: Extended (CAD) | O41: Extended if US-made (CAD)
A42: Balance – 30ct | B42: China direct | C42: ='Regular Finish – Top 3'!B25 -> 120 ml | D42: China | E42: ='Regular Finish – Top 3'!I25+'Regular Finish – Top 3'!K25 -> 0.49 | F42: ='Regular Finish – Top 3'!L25 -> 1.424 | G42: =E42*F42*(1+Inputs!$B$33) -> 0.69776 | H42: 0 | I42: =(Inputs!$B$28+Inputs!$B$30)/(Inputs!$B$5+Inputs!$B$6) -> 0.664 | J42: =G42+H42+I42 -> 1.36176 | K42: 0 | L42: =J42+K42 -> 1.36176 | M42: =Inputs!$B$5 -> 2000 | N42: =J42*M42 -> 2723.52 | O42: =L42*M42 -> 2723.52
A43: New A – 60ct | B43: China direct | C43: ='Regular Finish – Top 3'!B26 -> 180–190 ml | D43: China | E43: ='Regular Finish – Top 3'!I26+'Regular Finish – Top 3'!K26 -> 0.55 | F43: ='Regular Finish – Top 3'!L26 -> 1.424 | G43: =E43*F43*(1+Inputs!$B$33) -> 0.7832 | H43: 0 | I43: =(Inputs!$B$28+Inputs!$B$30)/(Inputs!$B$5+Inputs!$B$6) -> 0.664 | J43: =G43+H43+I43 -> 1.4472 | K43: 0 | L43: =J43+K43 -> 1.4472 | M43: =Inputs!$B$6 -> 500 | N43: =J43*M43 -> 723.6 | O43: =L43*M43 -> 723.6
A44: New B – 90ct | B44: Burch 6 oz (local, 1 pallet) | C44: ='Regular Finish – Top 3'!B8 -> 6 oz | D44: US | E44: ='Regular Finish – Top 3'!I8+'Regular Finish – Top 3'!K8 -> 0.8075 | F44: ='Regular Finish – Top 3'!L8 -> 1.424 | G44: =E44*F44*(1+Inputs!$B$33) -> 1.14988 | H44: 0 | I44: =(Inputs!$B$24*Inputs!$B$10+Inputs!$B$25)/Inputs!$B$7 -> 1.3892 | J44: =G44+H44+I44 -> 2.53908 | K44: ='Regular Finish – Top 3'!I8*F44*Inputs!$B$34 -> 0.48238 | L44: =J44+K44 -> 3.02146 | M44: =Inputs!$B$7 -> 500 | N44: =J44*M44 -> 1269.54 | O44: =L44*M44 -> 1510.73
A45: TOTAL / average | J45: =N45/M45 -> 1.57222 | L45: =O45/M45 -> 1.6526167 | M45: =SUM(M42:M44) -> 3000 | N45: =SUM(N42:N44) -> 4716.66 | O45: =SUM(O42:O44) -> 4957.85
A47: R-B2 – 90ct local (Burch 9 oz) · Balance + 60ct from China
A48: SKU | B48: Source | C48: Jar | D48: Ships from | E48: Jar + cap price (native) | F48: FX | G48: Goods (CAD/unit) | H48: Frosting (CAD/unit) | I48: Freight & one-time (CAD/unit) | J48: LANDED (CAD/unit) | K48: 50% surtax if US-made (CAD/unit) | L48: LANDED if US-made | M48: Qty | N48: Extended (CAD) | O48: Extended if US-made (CAD)
A49: Balance – 30ct | B49: China direct | C49: ='Regular Finish – Top 3'!B25 -> 120 ml | D49: China | E49: ='Regular Finish – Top 3'!I25+'Regular Finish – Top 3'!K25 -> 0.49 | F49: ='Regular Finish – Top 3'!L25 -> 1.424 | G49: =E49*F49*(1+Inputs!$B$33) -> 0.69776 | H49: 0 | I49: =(Inputs!$B$28+Inputs!$B$30)/(Inputs!$B$5+Inputs!$B$6) -> 0.664 | J49: =G49+H49+I49 -> 1.36176 | K49: 0 | L49: =J49+K49 -> 1.36176 | M49: =Inputs!$B$5 -> 2000 | N49: =J49*M49 -> 2723.52 | O49: =L49*M49 -> 2723.52
A50: New A – 60ct | B50: China direct | C50: ='Regular Finish – Top 3'!B26 -> 180–190 ml | D50: China | E50: ='Regular Finish – Top 3'!I26+'Regular Finish – Top 3'!K26 -> 0.55 | F50: ='Regular Finish – Top 3'!L26 -> 1.424 | G50: =E50*F50*(1+Inputs!$B$33) -> 0.7832 | H50: 0 | I50: =(Inputs!$B$28+Inputs!$B$30)/(Inputs!$B$5+Inputs!$B$6) -> 0.664 | J50: =G50+H50+I50 -> 1.4472 | K50: 0 | L50: =J50+K50 -> 1.4472 | M50: =Inputs!$B$6 -> 500 | N50: =J50*M50 -> 723.6 | O50: =L50*M50 -> 723.6
A51: New B – 90ct | B51: Burch (local, 1 pallet) | C51: ='Regular Finish – Top 3'!B9 -> 9 oz | D51: US | E51: ='Regular Finish – Top 3'!I9+'Regular Finish – Top 3'!K9 -> 0.61083333 | F51: ='Regular Finish – Top 3'!L9 -> 1.424 | G51: =E51*F51*(1+Inputs!$B$33) -> 0.86982667 | H51: 0 | I51: =(Inputs!$B$24*Inputs!$B$10+Inputs!$B$25)/Inputs!$B$7 -> 1.3892 | J51: =G51+H51+I51 -> 2.2590267 | K51: ='Regular Finish – Top 3'!I9*F51*Inputs!$B$34 -> 0.31387333 | L51: =J51+K51 -> 2.5729 | M51: =Inputs!$B$7 -> 500 | N51: =J51*M51 -> 1129.5133 | O51: =L51*M51 -> 1286.45
A52: TOTAL / average | J52: =N52/M52 -> 1.5255444 | L52: =O52/M52 -> 1.5778567 | M52: =SUM(M49:M51) -> 3000 | N52: =SUM(N49:N51) -> 4576.6333 | O52: =SUM(O49:O51) -> 4733.57
A54: R-B2c – 90ct local (Richards 9 oz, Canadian stock) · Balance + 60ct from China
A55: SKU | B55: Source | C55: Jar | D55: Ships from | E55: Jar + cap price (native) | F55: FX | G55: Goods (CAD/unit) | H55: Frosting (CAD/unit) | I55: Freight & one-time (CAD/unit) | J55: LANDED (CAD/unit) | K55: 50% surtax if US-made (CAD/unit) | L55: LANDED if US-made | M55: Qty | N55: Extended (CAD) | O55: Extended if US-made (CAD)
A56: Balance – 30ct | B56: China direct | C56: ='Regular Finish – Top 3'!B25 -> 120 ml | D56: China | E56: ='Regular Finish – Top 3'!I25+'Regular Finish – Top 3'!K25 -> 0.49 | F56: ='Regular Finish – Top 3'!L25 -> 1.424 | G56: =E56*F56*(1+Inputs!$B$33) -> 0.69776 | H56: 0 | I56: =(Inputs!$B$28+Inputs!$B$30)/(Inputs!$B$5+Inputs!$B$6) -> 0.664 | J56: =G56+H56+I56 -> 1.36176 | K56: 0 | L56: =J56+K56 -> 1.36176 | M56: =Inputs!$B$5 -> 2000 | N56: =J56*M56 -> 2723.52 | O56: =L56*M56 -> 2723.52
A57: New A – 60ct | B57: China direct | C57: ='Regular Finish – Top 3'!B26 -> 180–190 ml | D57: China | E57: ='Regular Finish – Top 3'!I26+'Regular Finish – Top 3'!K26 -> 0.55 | F57: ='Regular Finish – Top 3'!L26 -> 1.424 | G57: =E57*F57*(1+Inputs!$B$33) -> 0.7832 | H57: 0 | I57: =(Inputs!$B$28+Inputs!$B$30)/(Inputs!$B$5+Inputs!$B$6) -> 0.664 | J57: =G57+H57+I57 -> 1.4472 | K57: 0 | L57: =J57+K57 -> 1.4472 | M57: =Inputs!$B$6 -> 500 | N57: =J57*M57 -> 723.6 | O57: =L57*M57 -> 723.6
A58: New B – 90ct | B58: Richards (Canada, 1 pallet) | C58: ='Regular Finish – Top 3'!B36 -> 9 oz | D58: Canada | E58: ='Regular Finish – Top 3'!I36+'Regular Finish – Top 3'!K36 -> 1.24 | F58: ='Regular Finish – Top 3'!L36 -> 1 | G58: =E58*F58*(1+Inputs!$B$33) -> 1.24 | H58: 0 | I58: =Inputs!$B$26/Inputs!$B$7 -> 0.3 | J58: =G58+H58+I58 -> 1.54 | K58: 0 | L58: =J58+K58 -> 1.54 | M58: =Inputs!$B$7 -> 500 | N58: =J58*M58 -> 770 | O58: =L58*M58 -> 770
A59: TOTAL / average | J59: =N59/M59 -> 1.4057067 | L59: =O59/M59 -> 1.4057067 | M59: =SUM(M56:M58) -> 3000 | N59: =SUM(N56:N58) -> 4217.12 | O59: =SUM(O56:O58) -> 4217.12
A61: R-C – All from China (reference – too slow for the urgent launch)
A62: SKU | B62: Source | C62: Jar | D62: Ships from | E62: Jar + cap price (native) | F62: FX | G62: Goods (CAD/unit) | H62: Frosting (CAD/unit) | I62: Freight & one-time (CAD/unit) | J62: LANDED (CAD/unit) | K62: 50% surtax if US-made (CAD/unit) | L62: LANDED if US-made | M62: Qty | N62: Extended (CAD) | O62: Extended if US-made (CAD)
A63: Balance – 30ct | B63: China direct | C63: ='Regular Finish – Top 3'!B25 -> 120 ml | D63: China | E63: ='Regular Finish – Top 3'!I25+'Regular Finish – Top 3'!K25 -> 0.49 | F63: ='Regular Finish – Top 3'!L25 -> 1.424 | G63: =E63*F63*(1+Inputs!$B$33) -> 0.69776 | H63: 0 | I63: =(Inputs!$B$21+Inputs!$B$30)/Inputs!$B$8 -> 0.61666667 | J63: =G63+H63+I63 -> 1.3144267 | K63: 0 | L63: =J63+K63 -> 1.3144267 | M63: =Inputs!$B$5 -> 2000 | N63: =J63*M63 -> 2628.8533 | O63: =L63*M63 -> 2628.8533
A64: New A – 60ct | B64: China direct | C64: ='Regular Finish – Top 3'!B26 -> 180–190 ml | D64: China | E64: ='Regular Finish – Top 3'!I26+'Regular Finish – Top 3'!K26 -> 0.55 | F64: ='Regular Finish – Top 3'!L26 -> 1.424 | G64: =E64*F64*(1+Inputs!$B$33) -> 0.7832 | H64: 0 | I64: =(Inputs!$B$21+Inputs!$B$30)/Inputs!$B$8 -> 0.61666667 | J64: =G64+H64+I64 -> 1.3998667 | K64: 0 | L64: =J64+K64 -> 1.3998667 | M64: =Inputs!$B$6 -> 500 | N64: =J64*M64 -> 699.93333 | O64: =L64*M64 -> 699.93333
A65: New B – 90ct | B65: China direct | C65: ='Regular Finish – Top 3'!B27 -> 250 ml | D65: China | E65: ='Regular Finish – Top 3'!I27+'Regular Finish – Top 3'!K27 -> 0.49 | F65: ='Regular Finish – Top 3'!L27 -> 1.424 | G65: =E65*F65*(1+Inputs!$B$33) -> 0.69776 | H65: 0 | I65: =(Inputs!$B$21+Inputs!$B$30)/Inputs!$B$8 -> 0.61666667 | J65: =G65+H65+I65 -> 1.3144267 | K65: 0 | L65: =J65+K65 -> 1.3144267 | M65: =Inputs!$B$7 -> 500 | N65: =J65*M65 -> 657.21333 | O65: =L65*M65 -> 657.21333
A66: TOTAL / average | J66: =N66/M66 -> 1.3286667 | L66: =O66/M66 -> 1.3286667 | M66: =SUM(M63:M65) -> 3000 | N66: =SUM(N63:N65) -> 3986 | O66: =SUM(O63:O65) -> 3986
A68: FROSTED amber – scenario detail
A69: F-A – All local: Burch 4/6/9 oz + Canadian spray-frost
A70: SKU | B70: Source | C70: Jar | D70: Ships from | E70: Jar + cap price (native) | F70: FX | G70: Goods (CAD/unit) | H70: Frosting (CAD/unit) | I70: Freight & one-time (CAD/unit) | J70: LANDED (CAD/unit) | K70: 50% surtax if US-made (CAD/unit) | L70: LANDED if US-made | M70: Qty | N70: Extended (CAD) | O70: Extended if US-made (CAD)
A71: Balance – 30ct | B71: Burch + spray frost | C71: ='Regular Finish – Top 3'!B7 -> 4 oz | D71: US | E71: ='Regular Finish – Top 3'!I7+'Regular Finish – Top 3'!K7 -> 0.61708333 | F71: ='Regular Finish – Top 3'!L7 -> 1.424 | G71: =E71*F71*(1+Inputs!$B$33) -> 0.87872667 | H71: =Inputs!$B$37+(Inputs!$B$38*Inputs!$B$9+Inputs!$B$39)/Inputs!$B$8 -> 1.2 | I71: =(Inputs!$B$18*Inputs!$B$10+Inputs!$B$19)/Inputs!$B$8 -> 0.36686667 | J71: =G71+H71+I71 -> 2.4455933 | K71: ='Regular Finish – Top 3'!I7*F71*Inputs!$B$34 -> 0.33968333 | L71: =J71+K71 -> 2.7852767 | M71: =Inputs!$B$5 -> 2000 | N71: =J71*M71 -> 4891.1867 | O71: =L71*M71 -> 5570.5533
A72: New A – 60ct | B72: Burch + spray frost | C72: ='Regular Finish – Top 3'!B8 -> 6 oz | D72: US | E72: ='Regular Finish – Top 3'!I8+'Regular Finish – Top 3'!K8 -> 0.8075 | F72: ='Regular Finish – Top 3'!L8 -> 1.424 | G72: =E72*F72*(1+Inputs!$B$33) -> 1.14988 | H72: =Inputs!$B$37+(Inputs!$B$38*Inputs!$B$9+Inputs!$B$39)/Inputs!$B$8 -> 1.2 | I72: =(Inputs!$B$18*Inputs!$B$10+Inputs!$B$19)/Inputs!$B$8 -> 0.36686667 | J72: =G72+H72+I72 -> 2.7167467 | K72: ='Regular Finish – Top 3'!I8*F72*Inputs!$B$34 -> 0.48238 | L72: =J72+K72 -> 3.1991267 | M72: =Inputs!$B$6 -> 500 | N72: =J72*M72 -> 1358.3733 | O72: =L72*M72 -> 1599.5633
A73: New B – 90ct | B73: Burch + spray frost | C73: ='Regular Finish – Top 3'!B9 -> 9 oz | D73: US | E73: ='Regular Finish – Top 3'!I9+'Regular Finish – Top 3'!K9 -> 0.61083333 | F73: ='Regular Finish – Top 3'!L9 -> 1.424 | G73: =E73*F73*(1+Inputs!$B$33) -> 0.86982667 | H73: =Inputs!$B$37+(Inputs!$B$38*Inputs!$B$9+Inputs!$B$39)/Inputs!$B$8 -> 1.2 | I73: =(Inputs!$B$18*Inputs!$B$10+Inputs!$B$19)/Inputs!$B$8 -> 0.36686667 | J73: =G73+H73+I73 -> 2.4366933 | K73: ='Regular Finish – Top 3'!I9*F73*Inputs!$B$34 -> 0.31387333 | L73: =J73+K73 -> 2.7505667 | M73: =Inputs!$B$7 -> 500 | N73: =J73*M73 -> 1218.3467 | O73: =L73*M73 -> 1375.2833
A74: TOTAL / average | J74: =N74/M74 -> 2.4893022 | L74: =O74/M74 -> 2.8484667 | M74: =SUM(M71:M73) -> 3000 | N74: =SUM(N71:N73) -> 7467.9067 | O74: =SUM(O71:O73) -> 8545.4
A76: F-B1 – FLEX PLAN, outcome 90ct = size 00: 6 oz (Burch + spray frost) local → 60ct · Balance + 90ct frosted from China
A77: SKU | B77: Source | C77: Jar | D77: Ships from | E77: Jar + cap price (native) | F77: FX | G77: Goods (CAD/unit) | H77: Frosting (CAD/unit) | I77: Freight & one-time (CAD/unit) | J77: LANDED (CAD/unit) | K77: 50% surtax if US-made (CAD/unit) | L77: LANDED if US-made | M77: Qty | N77: Extended (CAD) | O77: Extended if US-made (CAD)
A78: Balance – 30ct | B78: China direct (frosted) | C78: ='Frosted Finish – Top 3'!B7 -> 120 ml | D78: China | E78: ='Frosted Finish – Top 3'!I7+'Frosted Finish – Top 3'!K7 -> 0.53 | F78: ='Frosted Finish – Top 3'!L7 -> 1.424 | G78: =E78*F78*(1+Inputs!$B$33) -> 0.75472 | H78: 0 | I78: =(Inputs!$B$27+Inputs!$B$30)/(Inputs!$B$5+Inputs!$B$7) -> 0.672 | J78: =G78+H78+I78 -> 1.42672 | K78: 0 | L78: =J78+K78 -> 1.42672 | M78: =Inputs!$B$5 -> 2000 | N78: =J78*M78 -> 2853.44 | O78: =L78*M78 -> 2853.44
A79: New A – 60ct | B79: Burch + spray frost (1 pallet) | C79: ='Regular Finish – Top 3'!B8 -> 6 oz | D79: US | E79: ='Regular Finish – Top 3'!I8+'Regular Finish – Top 3'!K8 -> 0.8075 | F79: ='Regular Finish – Top 3'!L8 -> 1.424 | G79: =E79*F79*(1+Inputs!$B$33) -> 1.14988 | H79: =Inputs!$B$37+(Inputs!$B$38+Inputs!$B$39)/Inputs!$B$6 -> 2.35 | I79: =(Inputs!$B$24*Inputs!$B$10+Inputs!$B$25)/Inputs!$B$6 -> 1.3892 | J79: =G79+H79+I79 -> 4.88908 | K79: ='Regular Finish – Top 3'!I8*F79*Inputs!$B$34 -> 0.48238 | L79: =J79+K79 -> 5.37146 | M79: =Inputs!$B$6 -> 500 | N79: =J79*M79 -> 2444.54 | O79: =L79*M79 -> 2685.73
A80: New B – 90ct | B80: China direct (frosted) | C80: ='Frosted Finish – Top 3'!B9 -> 250 ml | D80: China | E80: ='Frosted Finish – Top 3'!I9+'Frosted Finish – Top 3'!K9 -> 0.62 | F80: ='Frosted Finish – Top 3'!L9 -> 1.424 | G80: =E80*F80*(1+Inputs!$B$33) -> 0.88288 | H80: 0 | I80: =(Inputs!$B$27+Inputs!$B$30)/(Inputs!$B$5+Inputs!$B$7) -> 0.672 | J80: =G80+H80+I80 -> 1.55488 | K80: 0 | L80: =J80+K80 -> 1.55488 | M80: =Inputs!$B$7 -> 500 | N80: =J80*M80 -> 777.44 | O80: =L80*M80 -> 777.44
A81: TOTAL / average | J81: =N81/M81 -> 2.02514 | L81: =O81/M81 -> 2.1055367 | M81: =SUM(M78:M80) -> 3000 | N81: =SUM(N78:N80) -> 6075.42 | O81: =SUM(O78:O80) -> 6316.61
A83: F-FX0 – FLEX PLAN, outcome 90ct = size 0: 6 oz (Burch + spray frost) local → 90ct · Balance + 60ct frosted (6 oz) from China
A84: SKU | B84: Source | C84: Jar | D84: Ships from | E84: Jar + cap price (native) | F84: FX | G84: Goods (CAD/unit) | H84: Frosting (CAD/unit) | I84: Freight & one-time (CAD/unit) | J84: LANDED (CAD/unit) | K84: 50% surtax if US-made (CAD/unit) | L84: LANDED if US-made | M84: Qty | N84: Extended (CAD) | O84: Extended if US-made (CAD)
A85: Balance – 30ct | B85: China direct (frosted) | C85: ='Frosted Finish – Top 3'!B7 -> 120 ml | D85: China | E85: ='Frosted Finish – Top 3'!I7+'Frosted Finish – Top 3'!K7 -> 0.53 | F85: ='Frosted Finish – Top 3'!L7 -> 1.424 | G85: =E85*F85*(1+Inputs!$B$33) -> 0.75472 | H85: 0 | I85: =(Inputs!$B$28+Inputs!$B$30)/(Inputs!$B$5+Inputs!$B$6) -> 0.664 | J85: =G85+H85+I85 -> 1.41872 | K85: 0 | L85: =J85+K85 -> 1.41872 | M85: =Inputs!$B$5 -> 2000 | N85: =J85*M85 -> 2837.44 | O85: =L85*M85 -> 2837.44
A86: New A – 60ct | B86: China direct (frosted) | C86: ='Frosted Finish – Top 3'!B8 -> 180–190 ml | D86: China | E86: ='Frosted Finish – Top 3'!I8+'Frosted Finish – Top 3'!K8 -> 0.67 | F86: ='Frosted Finish – Top 3'!L8 -> 1.424 | G86: =E86*F86*(1+Inputs!$B$33) -> 0.95408 | H86: 0 | I86: =(Inputs!$B$28+Inputs!$B$30)/(Inputs!$B$5+Inputs!$B$6) -> 0.664 | J86: =G86+H86+I86 -> 1.61808 | K86: 0 | L86: =J86+K86 -> 1.61808 | M86: =Inputs!$B$6 -> 500 | N86: =J86*M86 -> 809.04 | O86: =L86*M86 -> 809.04
A87: New B – 90ct | B87: Burch 6 oz + spray frost (1 pallet) | C87: ='Regular Finish – Top 3'!B8 -> 6 oz | D87: US | E87: ='Regular Finish – Top 3'!I8+'Regular Finish – Top 3'!K8 -> 0.8075 | F87: ='Regular Finish – Top 3'!L8 -> 1.424 | G87: =E87*F87*(1+Inputs!$B$33) -> 1.14988 | H87: =Inputs!$B$37+(Inputs!$B$38+Inputs!$B$39)/Inputs!$B$7 -> 2.35 | I87: =(Inputs!$B$24*Inputs!$B$10+Inputs!$B$25)/Inputs!$B$7 -> 1.3892 | J87: =G87+H87+I87 -> 4.88908 | K87: ='Regular Finish – Top 3'!I8*F87*Inputs!$B$34 -> 0.48238 | L87: =J87+K87 -> 5.37146 | M87: =Inputs!$B$7 -> 500 | N87: =J87*M87 -> 2444.54 | O87: =L87*M87 -> 2685.73
A88: TOTAL / average | J88: =N88/M88 -> 2.03034 | L88: =O88/M88 -> 2.1107367 | M88: =SUM(M85:M87) -> 3000 | N88: =SUM(N85:N87) -> 6091.02 | O88: =SUM(O85:O87) -> 6332.21
A90: F-B2 – 90ct local (Burch 9 oz + spray frost) · Balance + 60ct frosted from China
A91: SKU | B91: Source | C91: Jar | D91: Ships from | E91: Jar + cap price (native) | F91: FX | G91: Goods (CAD/unit) | H91: Frosting (CAD/unit) | I91: Freight & one-time (CAD/unit) | J91: LANDED (CAD/unit) | K91: 50% surtax if US-made (CAD/unit) | L91: LANDED if US-made | M91: Qty | N91: Extended (CAD) | O91: Extended if US-made (CAD)
A92: Balance – 30ct | B92: China direct (frosted) | C92: ='Frosted Finish – Top 3'!B7 -> 120 ml | D92: China | E92: ='Frosted Finish – Top 3'!I7+'Frosted Finish – Top 3'!K7 -> 0.53 | F92: ='Frosted Finish – Top 3'!L7 -> 1.424 | G92: =E92*F92*(1+Inputs!$B$33) -> 0.75472 | H92: 0 | I92: =(Inputs!$B$28+Inputs!$B$30)/(Inputs!$B$5+Inputs!$B$6) -> 0.664 | J92: =G92+H92+I92 -> 1.41872 | K92: 0 | L92: =J92+K92 -> 1.41872 | M92: =Inputs!$B$5 -> 2000 | N92: =J92*M92 -> 2837.44 | O92: =L92*M92 -> 2837.44
A93: New A – 60ct | B93: China direct (frosted) | C93: ='Frosted Finish – Top 3'!B8 -> 180–190 ml | D93: China | E93: ='Frosted Finish – Top 3'!I8+'Frosted Finish – Top 3'!K8 -> 0.67 | F93: ='Frosted Finish – Top 3'!L8 -> 1.424 | G93: =E93*F93*(1+Inputs!$B$33) -> 0.95408 | H93: 0 | I93: =(Inputs!$B$28+Inputs!$B$30)/(Inputs!$B$5+Inputs!$B$6) -> 0.664 | J93: =G93+H93+I93 -> 1.61808 | K93: 0 | L93: =J93+K93 -> 1.61808 | M93: =Inputs!$B$6 -> 500 | N93: =J93*M93 -> 809.04 | O93: =L93*M93 -> 809.04
A94: New B – 90ct | B94: Burch + spray frost (1 pallet) | C94: ='Regular Finish – Top 3'!B9 -> 9 oz | D94: US | E94: ='Regular Finish – Top 3'!I9+'Regular Finish – Top 3'!K9 -> 0.61083333 | F94: ='Regular Finish – Top 3'!L9 -> 1.424 | G94: =E94*F94*(1+Inputs!$B$33) -> 0.86982667 | H94: =Inputs!$B$37+(Inputs!$B$38+Inputs!$B$39)/Inputs!$B$7 -> 2.35 | I94: =(Inputs!$B$24*Inputs!$B$10+Inputs!$B$25)/Inputs!$B$7 -> 1.3892 | J94: =G94+H94+I94 -> 4.6090267 | K94: ='Regular Finish – Top 3'!I9*F94*Inputs!$B$34 -> 0.31387333 | L94: =J94+K94 -> 4.9229 | M94: =Inputs!$B$7 -> 500 | N94: =J94*M94 -> 2304.5133 | O94: =L94*M94 -> 2461.45
A95: TOTAL / average | J95: =N95/M95 -> 1.9836644 | L95: =O95/M95 -> 2.0359767 | M95: =SUM(M92:M94) -> 3000 | N95: =SUM(N92:N94) -> 5950.9933 | O95: =SUM(O92:O94) -> 6107.93
A97: F-B2s – 90ct local (Liquid Bottles 9 oz stock frosted) · Balance + 60ct frosted from China
A98: SKU | B98: Source | C98: Jar | D98: Ships from | E98: Jar + cap price (native) | F98: FX | G98: Goods (CAD/unit) | H98: Frosting (CAD/unit) | I98: Freight & one-time (CAD/unit) | J98: LANDED (CAD/unit) | K98: 50% surtax if US-made (CAD/unit) | L98: LANDED if US-made | M98: Qty | N98: Extended (CAD) | O98: Extended if US-made (CAD)
A99: Balance – 30ct | B99: China direct (frosted) | C99: ='Frosted Finish – Top 3'!B7 -> 120 ml | D99: China | E99: ='Frosted Finish – Top 3'!I7+'Frosted Finish – Top 3'!K7 -> 0.53 | F99: ='Frosted Finish – Top 3'!L7 -> 1.424 | G99: =E99*F99*(1+Inputs!$B$33) -> 0.75472 | H99: 0 | I99: =(Inputs!$B$28+Inputs!$B$30)/(Inputs!$B$5+Inputs!$B$6) -> 0.664 | J99: =G99+H99+I99 -> 1.41872 | K99: 0 | L99: =J99+K99 -> 1.41872 | M99: =Inputs!$B$5 -> 2000 | N99: =J99*M99 -> 2837.44 | O99: =L99*M99 -> 2837.44
A100: New A – 60ct | B100: China direct (frosted) | C100: ='Frosted Finish – Top 3'!B8 -> 180–190 ml | D100: China | E100: ='Frosted Finish – Top 3'!I8+'Frosted Finish – Top 3'!K8 -> 0.67 | F100: ='Frosted Finish – Top 3'!L8 -> 1.424 | G100: =E100*F100*(1+Inputs!$B$33) -> 0.95408 | H100: 0 | I100: =(Inputs!$B$28+Inputs!$B$30)/(Inputs!$B$5+Inputs!$B$6) -> 0.664 | J100: =G100+H100+I100 -> 1.61808 | K100: 0 | L100: =J100+K100 -> 1.61808 | M100: =Inputs!$B$6 -> 500 | N100: =J100*M100 -> 809.04 | O100: =L100*M100 -> 809.04
A101: New B – 90ct | B101: Liquid Bottles frosted (1 pallet) | C101: ='Frosted Finish – Top 3'!B36 -> 9 oz | D101: US | E101: ='Frosted Finish – Top 3'!I36+'Frosted Finish – Top 3'!K36 -> 1.88 | F101: ='Frosted Finish – Top 3'!L36 -> 1.424 | G101: =E101*F101*(1+Inputs!$B$33) -> 2.67712 | H101: 0 | I101: =(Inputs!$B$24*Inputs!$B$10+Inputs!$B$25)/Inputs!$B$7 -> 1.3892 | J101: =G101+H101+I101 -> 4.06632 | K101: ='Frosted Finish – Top 3'!I36*F101*Inputs!$B$34 -> 1.11784 | L101: =J101+K101 -> 5.18416 | M101: =Inputs!$B$7 -> 500 | N101: =J101*M101 -> 2033.16 | O101: =L101*M101 -> 2592.08
A102: TOTAL / average | J102: =N102/M102 -> 1.8932133 | L102: =O102/M102 -> 2.07952 | M102: =SUM(M99:M101) -> 3000 | N102: =SUM(N99:N101) -> 5679.64 | O102: =SUM(O99:O101) -> 6238.56
A104: F-C – All frosted from China (reference – too slow for the urgent launch)
A105: SKU | B105: Source | C105: Jar | D105: Ships from | E105: Jar + cap price (native) | F105: FX | G105: Goods (CAD/unit) | H105: Frosting (CAD/unit) | I105: Freight & one-time (CAD/unit) | J105: LANDED (CAD/unit) | K105: 50% surtax if US-made (CAD/unit) | L105: LANDED if US-made | M105: Qty | N105: Extended (CAD) | O105: Extended if US-made (CAD)
A106: Balance – 30ct | B106: China direct (frosted) | C106: ='Frosted Finish – Top 3'!B7 -> 120 ml | D106: China | E106: ='Frosted Finish – Top 3'!I7+'Frosted Finish – Top 3'!K7 -> 0.53 | F106: ='Frosted Finish – Top 3'!L7 -> 1.424 | G106: =E106*F106*(1+Inputs!$B$33) -> 0.75472 | H106: 0 | I106: =(Inputs!$B$21+Inputs!$B$30)/Inputs!$B$8 -> 0.61666667 | J106: =G106+H106+I106 -> 1.3713867 | K106: 0 | L106: =J106+K106 -> 1.3713867 | M106: =Inputs!$B$5 -> 2000 | N106: =J106*M106 -> 2742.7733 | O106: =L106*M106 -> 2742.7733
A107: New A – 60ct | B107: China direct (frosted) | C107: ='Frosted Finish – Top 3'!B8 -> 180–190 ml | D107: China | E107: ='Frosted Finish – Top 3'!I8+'Frosted Finish – Top 3'!K8 -> 0.67 | F107: ='Frosted Finish – Top 3'!L8 -> 1.424 | G107: =E107*F107*(1+Inputs!$B$33) -> 0.95408 | H107: 0 | I107: =(Inputs!$B$21+Inputs!$B$30)/Inputs!$B$8 -> 0.61666667 | J107: =G107+H107+I107 -> 1.5707467 | K107: 0 | L107: =J107+K107 -> 1.5707467 | M107: =Inputs!$B$6 -> 500 | N107: =J107*M107 -> 785.37333 | O107: =L107*M107 -> 785.37333
A108: New B – 90ct | B108: China direct (frosted) | C108: ='Frosted Finish – Top 3'!B9 -> 250 ml | D108: China | E108: ='Frosted Finish – Top 3'!I9+'Frosted Finish – Top 3'!K9 -> 0.62 | F108: ='Frosted Finish – Top 3'!L9 -> 1.424 | G108: =E108*F108*(1+Inputs!$B$33) -> 0.88288 | H108: 0 | I108: =(Inputs!$B$21+Inputs!$B$30)/Inputs!$B$8 -> 0.61666667 | J108: =G108+H108+I108 -> 1.4995467 | K108: 0 | L108: =J108+K108 -> 1.4995467 | M108: =Inputs!$B$7 -> 500 | N108: =J108*M108 -> 749.77333 | O108: =L108*M108 -> 749.77333
A109: TOTAL / average | J109: =N109/M109 -> 1.4259733 | L109: =O109/M109 -> 1.4259733 | M109: =SUM(M106:M108) -> 3000 | N109: =SUM(N106:N108) -> 4277.92 | O109: =SUM(O106:O108) -> 4277.92

Sheet All Suppliers Screened
A1: Every supplier screened – raw findings
A2: Prices as indexed (native currency). 'Meets rules' = has a jar for each SKU that fits AND looks at least half full (needs ~4, ~6 and ~9 oz).
A4: Finish | B4: Supplier | C4: Location / ships from | D4: Amber straight-sided sizes offered | E4: Has ~6 oz? | F4: Meets rules? | G4: Indicative jar price (native) | H4: Caps | I4: Verdict | J4: Source URL
A5: Regular | B5: Burch Bottle & Packaging | C5: NY, USA (USD). Jar origin not stated; caps Made in USA | D5: 4 (58-400), 6 (63-400), 9 (70-400); NO amber 8 oz | E5: Yes | F5: Yes | G5: Live: 4oz $0.477 @2,000 · 6oz $0.678 @500 · 9oz $0.441 @500 | H5: Black PP $0.13–0.17; PS22 only on 70-400 ($0.30) | I5: TOP 3 – #1 (local) | J5: https://www.burchbottle.com/6oz-Amber-Straight-Sided-Jar-63-400
A6: Regular | B6: Fillmore Container | C6: PA, USA (USD); ships to Canada. Origin not stated | D6: 4, 6 (6.76 fl oz overflow), 9, 16 oz; no amber 8 oz | E6: Yes | F6: Yes | G6: Live: 4oz $0.540 @2,000 · 6oz $0.666 @500 · 9oz $0.529 @500 | H6: Black PP F217 $0.125–0.22 | I6: TOP 3 – #2 | J6: https://www.fillmorecontainer.com/6-oz-amber-straight-sided-jar-case-of-12.html
A7: Regular | B7: China direct – Xuzhou Das / Qingdao Giant / Sincereal / Xuzhou Selead / Qingdao Xinte | C7: China (USD FOB) | D7: 120 ml, 175–180 ml, 250 ml (Selead & Qingdao Giant list matching families) | E7: Yes (175–180 ml) | F7: Yes (via RFQ) | G7: Live: 120 ml $0.41–0.45; 180 ml $0.42 @200–999 (Sincereal); MOQs 200–10,000 | H7: Mostly METAL lids at low MOQ – specify PP + induction liner | I7: TOP 3 – #3 / Balance + 60ct | J7: https://daspacking.en.made-in-china.com/product/CdRGEuVYJmpN/China-Wholesale-2oz-4oz-8oz-60g-120g-250g-Frosted-Clear-Amber-Airtight-Straight-Sided-Round-Face-Cosmetic-Cream-Candle-Glass-Jar-and-Container-with-Lids.html
A8: Regular | B8: Containers & Packaging Supply | C8: ID, USA (USD); UPS rate shown online includes brokerage | D8: 4 (G850AM), 6 (G506AM), 9 (G842AM – unavailable) | E8: Yes | F8: Yes | G8: Live: 4oz $0.45 @2,000 (cheapest 4 oz) · 6oz $0.57 @500 (63-400 cap unavailable) | H8: 58-400 black foam $0.13–0.17; 70-400 black PS $0.15–0.23 | I8: Free samples (up to 10) – good for Balance | J8: https://www.containerandpackaging.com/products/glass-straight-sided-jar/g850am/
A9: Regular | B9: Richards Packaging | C9: Canada (CAD); jars made in China (verified) | D9: 4 oz, 9 oz | E9: No | F9: No (60ct) – 9 oz OK for 90ct | G9: Live list: 4oz $0.96 · 9oz $0.99 CAD (member price may be lower) | H9: 58-400 black PP $0.50; 70 mm black PP $0.25 (list) | I9: No surtax risk; local alternative | J9: https://www.richardspackaging.com/products/9-oz-amber-glass-straight-sided-jar-70-400-12-rp-1001a
A10: Regular | B10: Uline Canada | C10: Canada (CAD) | D10: 1, 2, 4, 8 oz | E10: No | F10: No (60ct) | G10: Live: 4oz $1.67 (phenolic) / $1.60 (metal cap) · 8oz $2.35 / $2.20, 3+ cases | H10: Cap included; phenolic & metal caps can't be induction sealed | I10: Fast Canadian fallback for the 90ct 8 oz | J10: https://www.uline.ca/Product/Detail/S-24533
A11: Regular | B11: SKS Bottle & Packaging | C11: NY, USA (USD); FREE UPS Ground to Ontario on US$500+ | D11: 4, 8 oz (70/400); no 6 oz | E11: No | F11: No (60ct) – 8 oz for 90ct | G11: Live: 8oz $0.88 (case 36) · 4oz $1.07 | H11: 70/400 black w/ foam induction liner $159.60/760; PS22 $167.20/760 | I11: Cheapest landed 8 oz for the 90ct | J11: https://www.sks-bottle.com/product/305037.html
A12: Regular | B12: Specialty Bottle | C12: WA, USA (USD) | D12: 4, 9 oz | E12: No | F12: No | G12: 4oz $0.80 at 1K–5K incl. lid; 9oz $1.06 | H12: Lid included | I12: Not shortlisted | J12: https://www.specialtybottle.com/glass-jars/amber-straight-sided/4oz-salv4a
A13: Regular | B13: The Bottle Depot | C13: Aventura FL, USA (USD) | D13: 4 (58-400), 6 (54-410), 8 (71-410) | E13: Yes (odd neck) | F13: Partly – non-standard necks | G13: Live: 4oz $0.624 · 6oz $0.764 · 8oz $1.097 | H13: Black PP PE-lined $0.30–0.55 | I13: Not shortlisted | J13: https://thebottledepot.co/collections/amber-glass-jars
A14: Regular | B14: Berlin Packaging | C14: USA; Canada via United Bottles (QC) | D14: 4, 9 oz | E14: No | F14: No | G14: ~$0.55 (4 oz), some out of stock | H14: Separate | I14: Not shortlisted | J14: https://www.berlinpackaging.com/5001b55-b-4-oz-amber-glass-straight-sided-squat-jars-cap-not-included/
A15: Regular | B15: O.Berk | C15: USA | D15: 2, 4, 8, 16, 32 oz | E15: No | F15: No | G15: Quote required | H15: — | I15: Not shortlisted | J15: https://www.oberk.com/product-spotlight/amber-straight-side-jars
... A27: Frosted | B27: SKS Bottle & Packaging | C27: NY, USA | D27: Frosted 2/4/8 oz – CLEAR, not amber | E27: No | F27: No | G27: 4oz $1.41–2.79 · 8oz $2.30 | H27: Induction caps available | I27: FAILS – not amber | J27: https://www.sks-bottle.com/product/10768.html
A28: Frosted | B28: Uline, Richards, Containers & Pkg, Specialty Bottle, TricorBraun | C28: — | D28: Plain amber only | E28: — | F28: No | G28: — | H28: — | I28: FAILS – no frosted amber

Sheet Next Steps & Questions
A1: Next steps before ordering
A3: # | B3: Who | C3: Action
A4: 1 | B4: Owner (manufacturer) | C4: Confirm with your manufacturer: (a) Will they fill jars you supply? (b) Can their line handle straight-sided jars (4 / 6 / 8 oz)? (c) How do they tamper-seal glass today: induction, PS liner or shrink band? Then get their bottle + lid cost into Inputs.
A5: 2 | B5: Procurement | C5: 90ct: request a quote from SKS for 500 × 8 oz amber (40530080.03S) + 760 × 70/400 induction-lined caps (2101-79B), free UPS to Ontario. Ask for COUNTRY OF ORIGIN of the jar (US-made = 50% surtax on the jar). Fallback: Uline S-24533/S-25207 (Canadian stock).
A6: 3 | B6: Procurement | C6: China RFQ to Qingdao Giant, Xuzhou Selead, Xuzhou Das, Chongqing Sincereal and VANJOIN: 2,000 × 120 ml + 500 × 180 ml from stock, matching style, regular AND frosted. Require 58-400 / 63-400 necks, black PP caps with induction or PS22 liners, brim-full capacity, drawings, FOB price, sample cost, lead time, carton data. Pay via Trade Assurance / secured trading.
A7: 4 | B7: Procurement | C7: LCL door-to-door quotes from 2–3 Canadian forwarders (1.0–1.3 m³, 350–450 kg glass, to your Ontario postal code), itemized with minimums, plus one DDP-per-m³ quote.
A8: 5 | B8: Procurement | C8: Local fallback quotes for Balance + 60ct: Burch (4 oz + 6 oz, one shipment, freight to your postal code, country of origin) and Richards member pricing (4 oz + caps). Order CPS free samples (G850AM 4 oz, G506AM 6 oz).
A9: 6 | B9: Owner + broker | C9: Ask a customs broker: (a) tariff suffix 7010.90.00.95 vs .96; (b) whether the US Surtax Remission Order covers US-made jars used to package supplements.
A10: 7 | B10: Owner + designer | C10: Decide bottle STYLE first (packer vs straight-sided – see the Packer vs Straight-Sided tab), then finish (regular vs frosted). Samples in hand: pour test – packers: 60 capsules in a 150cc, 90 in a 250cc; jars: 60 in a 6 oz, 90 in an 8 oz.
A11: 8 | B11: Owner | C11: If frosted: Stanpac quote for spray-frosting 500 × 8 oz (and which plant does it – Ontario or Wisconsin).
A13: Data caveats
A14: • North American prices were checked live on supplier websites on Oct 9, 2026. Alibaba blocked automated access, so some China data is from search snippets; made-in-china.com listings were checked live. Confirm everything by written quote.
A15: • Freight, brokerage, frosting and China prices are estimates (labelled on the Inputs sheet). Replace them with real quotes and the whole workbook recalculates.
A16: • The 50% surtax on US-made glass jars is CONFIRMED (SOR/2026-186, Schedule 3, tariff item 7010.90.00). Whether a remission/refund applies to supplement packaging needs a broker's opinion.
A17: • Jar volumes are nominal. Capsule fit and 'looks half full' are modelled (see Capsule Sizing) and must be confirmed with a fill test.
